{
  "munzee": 0,
  "greenie": 0,
  "normal": 0,
  "standard": 0,
  "premium": 1,
  "landmachtdagen": 2,
  "meetandgreetnetherlands": 3,
  "minnesotameetup": 4,
  "canadaswarm": 5,
  "h2oklan100k": 6,
  "marinedays": 7,
  "hamburgbbq": 8,
  "wamunzeeevent": 9,
  "stlouiscarrace": 10,
  "endoftheworld": 11,
  "euroambassador": 12,
  "social": 13,
  "munzeemadness2": 14,
  "egghunt": 15,
  "washingtonparks": 16,
  "emg": 17,
  "diamond": 18,
  "europeevent": 19,
  "europeeventrobje64": 20,
  "europeeventzeusi": 21,
  "europeeventpappapad": 22,
  "garlicbreathafterparty": 23,
  "mace": 24,
  "longsword": 25,
  "bierkrug": 26,
  "brezel": 27,
  "lederhosen": 28,
  "eventpin": 29,
  "1starmotel": 30,
  "1starmotelroom": 31,
  "teammunzeecanada": 32,
  "robvisitsdeutschland": 33,
  "pariscachebash": 34,
  "australiaday": 35,
  "mm3": 36,
  "mm3event": 37,
  "dinner": 38,
  "awfc5k": 39,
  "geowoodstock2014": 40,
  "foodtruckfrenzy": 41,
  "mwmb": 42,
  "spacecoast": 43,
  "obical": 44,
  "ruby": 45,
  "eaa": 46,
  "robsreturn": 47,
  "2ndeuropeevent": 48,
  "munzillaevent": 49,
  "battleaxe": 50,
  "socalmunzeecon": 51,
  "worldscollideseattle": 52,
  "massmunzeemania2014": 53,
  "kalispell2014": 54,
  "gchr2014": 55,
  "hhme": 56,
  "virtualemerald": 57,
  "gardenpin": 57,
  "rheinischerstammtischiv": 58,
  "springtimescrounge2014": 59,
  "munzeeween2014": 60,
  "berlin2014": 61,
  "firstofmany": 62,
  "ummg2014": 63,
  "owloween": 64,
  "biglittleevent2014": 65,
  "worldscollidevegas": 66,
  "camporee2014": 67,
  "jerseyartsquest2014": 68,
  "spacecoastmunzeefest": 69,
  "duckdynasty2014": 70,
  "chestnutghostwalk": 71,
  "midwestmunzeemadness2014": 72,
  "turkeytrot2014": 73,
  "munzeetreffeninberlin2014": 74,
  "hotel": 75,
  "hotelroom": 76,
  "frisian": 77,
  "kingsbridge": 78,
  "sonorandesertshowdown": 79,
  "cappingthecoast2014": 80,
  "moojahunt": 81,
  "luxembourggreetzberlin2014": 82,
  "cookiecrumbles2014": 83,
  "merrymunzmas2014": 84,
  "bearymerrymunzmas2014": 85,
  "missionbay2014": 86,
  "wdw2014": 87,
  "wintertraumstuttgart": 88,
  "gluehweinamdom": 89,
  "trail": 90,
  "suncoast2015": 91,
  "australiaday2015": 92,
  "aussierob": 93,
  "munzeebowl2015": 94,
  "ancientmarketkingston2015": 95,
  "personal": 96,
  "qrazyturnsone": 97,
  "aquamarine": 98,
  "topaz": 99,
  "mystery": 100,
  "virtualamethyst": 101,
  "eventindicator": 102,
  "nomad": 103,
  "nomadvirtual": 104,
  "thehammer": 105,
  "scorpio": 106,
  "sagittarius": 107,
  "capricorn": 108,
  "aquarius": 109,
  "pisces": 110,
  "aries": 111,
  "taurus": 112,
  "gemini": 113,
  "cancer": 114,
  "leo": 115,
  "virgo": 116,
  "libra": 117,
  "flatrob": 118,
  "virtualtrail": 119,
  "surprise": 120,
  "shamrock": 121,
  "prizewheel": 122,
  "scatter": 123,
  "theunicorn": 124,
  "unicornhost": 125,
  "leprechaun": 126,
  "leprechaunhost": 127,
  "munzeemadnessreseller": 128,
  "geostuffreseller": 129,
  "geohobbiesreseller": 130,
  "ddcardsreseller": 131,
  "negsreseller": 132,
  "geologgersreseller": 133,
  "mmcocoabeachreseller": 134,
  "nomadmystery": 135,
  "rockpaperscissors": 136,
  "firemystery": 137,
  "rujareseller": 138,
  "dragon": 139,
  "dragonhost": 140,
  "pinkdiamond": 141,
  "eventtrail": 142,
  "laupereseller": 143,
  "icemystery": 144,
  "tomato": 145,
  "earofcorn": 146,
  "carrot": 147,
  "peas": 148,
  "tomatoseed": 149,
  "cornseed": 150,
  "carrotseed": 151,
  "peasseed": 152,
  "tomatoplant": 153,
  "cornstalk": 154,
  "carrotplant": 155,
  "peasplant": 156,
  "goldencarrot": 157,
  "goldencarrotseed": 158,
  "goldencarrotplant": 159,
  "virtualsapphire": 160,
  "txhistoricallocation": 161,
  "milk": 162,
  "bacon": 163,
  "scgsreseller": 164,
  "calf": 165,
  "piglet": 166,
  "cow": 167,
  "pig": 168,
  "championshiphorse": 169,
  "horse": 169,
  "eggs": 170,
  "colt": 171,
  "chick": 172,
  "racehorse": 173,
  "chicken": 174,
  "barn": 175,
  "tractor": 176,
  "yeti": 177,
  "yetihost": 178,
  "leantoshed": 179,
  "gardenshed": 180,
  "hoe": 181,
  "plow": 182,
  "family": 183,
  "field": 184,
  "farmer": 185,
  "farmerandwife": 186,
  "pottedplant": 187,
  "garden": 188,
  "shark": 189,
  "seaweed": 190,
  "fish": 191,
  "submarine": 192,
  "canoe": 193,
  "motorboat": 194,
  "poiairport": 195,
  "poisports": 196,
  "poiuniversity": 197,
  "poimuseum": 198,
  "poiwildlife": 199,
  "egg": 200,
  "dinosaur": 201,
  "bones": 202,
  "musclecar": 203,
  "firstwheel": 204,
  "pennyfarthingbike": 205,
  "jewelthiefnomad": 206,
  "bellhopnomad": 207,
  "piratenomad": 208,
  "kingofthejungle": 209,
  "lioncub": 210,
  "lion": 211,
  "safaribus": 212,
  "safaritruck": 213,
  "safarivan": 214,
  "earthmystery": 215,
  "faun": 216,
  "faunhost": 217,
  "hydra": 218,
  "hydrahost": 219,
  "crossbow": 220,
  "warriornomad": 221,
  "mhqflatmatt": 222,
  "mhqflatrob": 223,
  "flatmatt": 224,
  "watermystery": 225,
  "coin": 226,
  "bagofcoins": 227,
  "treasurechest": 228,
  "airmystery": 229,
  "pegasus": 230,
  "pegasushost": 231,
  "premiumpersonal": 232,
  "springseasonal": 233,
  "summerseasonal": 234,
  "fallseasonal": 235,
  "winterseasonal": 236,
  "seasonal": 2173,
  "cyclops": 238,
  "cyclopshost": 239,
  "cyclopsvirtualhost": 240,
  "temporaryvirtual": 241,
  "tempvirt": 241,
  "briefcase": 242,
  "catapult": 243,
  "dogchinesezodiac": 244,
  "pigchinesezodiac": 245,
  "ratchinesezodiac": 246,
  "oxchinesezodiac": 247,
  "tigerchinesezodiac": 248,
  "rabbitchinesezodiac": 249,
  "dragonchinesezodiac": 250,
  "snakechinesezodiac": 251,
  "horsechinesezodiac": 252,
  "goatchinesezodiac": 253,
  "monkeychinesezodiac": 254,
  "roosterchinesezodiac": 255,
  "flatlou": 256,
  "poihistoricalplace": 257,
  "poilibrary": 258,
  "poifirstresponders": 259,
  "poifaithplace": 260,
  "poifaith": 260,
  "towerbridgeflatlou": 261,
  "nightvisiongoggles": 262,
  "nvgoggles": 262,
  "mermaid": 263,
  "mermaidhost": 264,
  "virtual": 265,
  "virtualrainbow": 266,
  "virtualtimberwolf": 267,
  "virtualsilver": 268,
  "virtualgray": 269,
  "virtualblack": 270,
  "virtualorchid": 271,
  "virtualwisteria": 272,
  "virtualpurplemountainsmajesty": 273,
  "virtualviolet": 274,
  "virtualplum": 275,
  "virtualblueviolet": 276,
  "virtualblue": 277,
  "virtualcadetblue": 278,
  "virtualperiwinkle": 279,
  "virtualcornflower": 280,
  "virtualbluegreen": 281,
  "virtualpacificblue": 282,
  "virtualcerulean": 283,
  "virtualrobineggblue": 284,
  "virtualindigo": 285,
  "virtualturquoiseblue": 286,
  "virtualseagreen": 287,
  "virtualgrannysmithapple": 288,
  "virtualgreen": 289,
  "virtualforestgreen": 290,
  "virtualasparagus": 291,
  "virtualolivegreen": 292,
  "virtualyellowgreen": 293,
  "virtualgreenyellow": 294,
  "virtualspringgreen": 295,
  "virtualgold": 296,
  "virtualyellow": 297,
  "virtualgoldenrod": 298,
  "virtualdandelion": 299,
  "virtualorange": 300,
  "virtualburntorange": 301,
  "virtualmelon": 302,
  "virtualpink": 303,
  "virtualcarnationpink": 304,
  "virtualmauvelous": 305,
  "virtualsalmon": 306,
  "virtualticklemepink": 307,
  "virtualmagenta": 308,
  "virtualwildstrawberry": 309,
  "virtualvioletred": 310,
  "virtualredviolet": 311,
  "virtualapricot": 312,
  "virtualpeach": 313,
  "virtualmacaroniandcheese": 314,
  "virtualtan": 315,
  "virtualburntsienna": 316,
  "virtualbittersweet": 317,
  "virtualredorange": 318,
  "virtualscarlet": 319,
  "virtualred": 320,
  "virtualbrickred": 321,
  "virtualmahogany": 322,
  "virtualchestnut": 323,
  "virtualtumbleweed": 324,
  "virtualrawsienna": 325,
  "virtualbrown": 326,
  "flhistoricallocation": 327,
  "cahistoricallocation": 328,
  "poihospital": 329,
  "poipostoffice": 330,
  "poicemetery": 331,
  "worldheritagehistoricallocation": 332,
  "retiredunicorn": 333,
  "retiredleprechaun": 334,
  "retireddragon": 335,
  "retiredyeti": 336,
  "fairy": 337,
  "fairyhost": 338,
  "fairyvirtualhost": 339,
  "poiuniqueattraction": 340,
  "greatbritainiconiclocation": 341,
  "travelernomad": 342,
  "flathammock": 343,
  "gettysburgflathammock": 344,
  "dryadfairy": 345,
  "wildfirefairy": 346,
  "battleunicorn": 347,
  "hippocampunicorn": 348,
  "poivirtualgarden": 349,
  "seasonalnomad": 350,
  "bowlingball": 351,
  "dwarfleprechaun": 352,
  "goblinleprechaun": 353,
  "hotspringmermaid": 354,
  "melusinemermaid": 355,
  "mermaidvirtualhost": 356,
  "leprechaunvirtualhost": 357,
  "virtualflatnomad": 358,
  "beachflatrob": 359,
  "coldflatrob": 360,
  "tuxflatrob": 361,
  "fancyflatrobhost": 362,
  "fancyflatrobvirtualhost": 363,
  "mitmegu": 364,
  "jootmegu": 365,
  "rohimegu": 366,
  "lokemegu": 367,
  "mitmegupouchcreaturehost": 368,
  "rose": 369,
  "tulip": 370,
  "czechrepubliciconiclocation": 371,
  "slovakiaiconiclocation": 372,
  "poicinema": 373,
  "lily": 374,
  "tulipseed": 375,
  "tulipgermination": 376,
  "tulipgrowth": 377,
  "tulipbud": 378,
  "bluetulipblossom": 379,
  "pinktulipblossom": 380,
  "whitetulipblossom": 381,
  "roseseed": 382,
  "rosegermination": 383,
  "rosegrowth": 384,
  "rosebud": 385,
  "redroseblossom": 386,
  "violetroseblossom": 387,
  "whiteroseblossom": 388,
  "yellowroseblossom": 389,
  "lilyseed": 390,
  "lilygermination": 391,
  "lilygrowth": 392,
  "lilybud": 393,
  "pinklilyblossom": 394,
  "violetlilyblossom": 395,
  "whitelilyblossom": 396,
  "carnation": 397,
  "carnationseed": 398,
  "carnationgermination": 399,
  "carnationgrowth": 400,
  "carnationbud": 401,
  "pinkcarnationblossom": 402,
  "redcarnationblossom": 403,
  "violetcarnationblossom": 404,
  "whitecarnationblossom": 405,
  "yellowcarnationblossom": 406,
  "urbanfit": 407,
  "banshee": 408,
  "bansheehost": 409,
  "bansheevirtualhost": 410,
  "washingtoniconiclocation": 411,
  "butterflyegg": 412,
  "caterpillar": 413,
  "chrysalis": 414,
  "hatchedchrysalis": 415,
  "gleamingmuru": 416,
  "gleamingmuruchi": 417,
  "gleamingmurutain": 418,
  "gleamingtuli": 419,
  "gleamingtulimber": 420,
  "gleamingtuliferno": 421,
  "gleamingvesi": 422,
  "gleamingvesial": 423,
  "gleamingvesisaur": 424,
  "chinesedragon": 425,
  "wyverndragon": 426,
  "lycanthropeyeti": 427,
  "reptoidyeti": 428,
  "dragonvirtualhost": 429,
  "qrewzee": 430,
  "pimedus": 431,
  "pimedushost": 432,
  "pimedusvirtualhost": 433,
  "joystick": 434,
  "poitransportation": 435,
  "poiplaypark": 436,
  "matterupflatmatt": 437,
  "faceoffflatmatt": 438,
  "footyflatmatt": 439,
  "fancyflatmatthost": 440,
  "fancyflatmattvirtualhost": 441,
  "griffinpegasus": 442,
  "alicornpegasus": 443,
  "centaurfaun": 444,
  "krampusfaun": 445,
  "pegasusphysicalhost": 446,
  "faunvirtualhost": 447,
  "joystickvirtual": 448,
  "internationelles": 449,
  "internationellesvirtual": 450,
  "frogegg": 451,
  "tadpole": 452,
  "pollywog": 453,
  "froglet": 454,
  "nymph": 455,
  "nymphhost": 456,
  "nymphvirtualhost": 457,
  "newhampshireiconiclocation": 458,
  "newmexicoiconiclocation": 459,
  "puffle": 460,
  "pufrain": 461,
  "puflawn": 462,
  "airpouchcreaturehost": 463,
  "cerberushydra": 464,
  "cthulhuhydra": 465,
  "harpybanshee": 466,
  "witchbanshee": 467,
  "magnetus": 468,
  "virtualcitrine": 469,
  "virtualonyx": 470,
  "topaas": 471,
  "ametust": 472,
  "oniks": 473,
  "teemant": 474,
  "smaragd": 475,
  "renovation": 476,
  "electricmystery": 477,
  "elekter": 478,
  "elekjoud": 479,
  "elektrivool": 480,
  "sirprizewheel": 481,
  "birthdaycard": 482,
  "getwellcard": 483,
  "earthdaycard1": 484,
  "earthdaycard2": 485,
  "earthdaycard3": 486,
  "stayhomecard": 487,
  "hammercorncard": 488,
  "clanwarcard": 489,
  "thankyoucard": 490,
  "worldlaughterdaycard": 491,
  "poibank": 492,
  "poibeach": 493,
  "poicampground": 494,
  "poigolf": 495,
  "howdycard": 496,
  "safetravelscard": 497,
  "turtleegg": 498,
  "turtlehatchling": 499,
  "juvenileturtle": 500,
  "adultturtle": 501,
  "planulalarva": 502,
  "polyp": 503,
  "polypwithbulbs": 504,
  "minotaurcyclops": 505,
  "balorcyclops": 506,
  "vampirenymph": 507,
  "elfnymph": 508,
  "congratscard": 509,
  "sorrycard": 510,
  "sorrycard1": 511,
  "sorrycard2": 512,
  "sorrycard3": 513,
  "mayflowerscard": 514,
  "poseidon": 515,
  "worldoceandaycard": 516,
  "summercard": 517,
  "wintercard": 518,
  "eventcard": 519,
  "tuli": 520,
  "tulimber": 521,
  "tuliferno": 522,
  "vesi": 523,
  "vesial": 524,
  "vesisaur": 525,
  "waterpouchcreaturehost": 526,
  "muru": 527,
  "muruchi": 528,
  "murutain": 529,
  "earthpouchcreaturehost": 530,
  "coupechampionnomad": 531,
  "coupechampions1": 532,
  "coupechampions2": 533,
  "coupechampions3": 534,
  "coupechampions4": 535,
  "coupechampions5": 536,
  "coupechampions6": 537,
  "coupechampions7": 538,
  "coupechampions8": 539,
  "coupechampions9": 540,
  "coupechampions10": 541,
  "coupechampions11": 542,
  "coupechampions12": 543,
  "coupechampions13": 544,
  "coupechampions14": 545,
  "coupechampions15": 546,
  "coupechampions16": 547,
  "coupechampions17": 548,
  "coupechampions18": 549,
  "coupechampions19": 550,
  "coupechampions20": 551,
  "coupechampions21": 552,
  "coupechampions22": 553,
  "coupechampions23": 554,
  "ephyralarva": 555,
  "akvamariin": 556,
  "rainbowunicorn": 557,
  "retiredfaun": 558,
  "retiredhydra": 559,
  "retiredmermaid": 560,
  "retiredpegasus": 561,
  "retiredcyclops": 562,
  "butterfly": 563,
  "morphobutterfly": 564,
  "monarchbutterfly": 565,
  "limebutterfly": 566,
  "butterflyhost": 567,
  "butterflyvirtualhost": 568,
  "retiredfairy": 569,
  "retiredbanshee": 570,
  "zombietuli": 571,
  "zombievesi": 572,
  "zombiemuru": 573,
  "frog": 574,
  "treefrog": 575,
  "poisondartfrog": 576,
  "tomatofrog": 577,
  "froghost": 578,
  "frogvirtualhost": 579,
  "hedgehog": 580,
  "polarbear": 581,
  "owlet": 582,
  "trojanunicorn": 583,
  "turtle": 584,
  "seaturtle": 585,
  "snappingturtle": 586,
  "taekwondotortoise": 587,
  "jellyfish": 588,
  "boxjellyfish": 589,
  "goldenjellyfish": 590,
  "pbjellyfish": 591,
  "scattered": 592,
  "fire": 593,
  "frozengreenie": 594,
  "waterdroplet": 595,
  "feather": 596,
  "goldenfeather": 597,
  "gnomeleprechaun": 598,
  "icedragon": 599,
  "sasquatchyeti": 600,
  "firepegasus": 601,
  "firepegasusphysicalhost": 602,
  "cherub": 603,
  "cherubvirtualhost": 604,
  "dossier": 605,
  "boulder": 606,
  "ogre": 607,
  "ogrehost": 608,
  "ogrevirtualhost": 609,
  "chimera": 610,
  "chimeravirtualhost": 611,
  "infraredvirtual": 612,
  "siren": 613,
  "fairygodmother": 614,
  "1stroll": 615,
  "2ndroll": 616,
  "hadavale": 617,
  "hadavalehost": 618,
  "hadavalevirtualhost": 619,
  "gorgon": 620,
  "runzeerob": 621,
  "goldcoin": 622,
  "leapfrog": 623,
  "fly": 624,
  "munchman": 625,
  "ghostzee": 626,
  "bowling1stroll": 627,
  "bowling2ndroll": 628,
  "motherearth": 629,
  "tree": 630,
  "spectacularspectacles2020vision": 631,
  "thekingssunglasses2020vision": 632,
  "weldinggoggles2020vision": 633,
  "flipglasses2020vision": 634,
  "skigoggles2020vision": 635,
  "theatrebinoculars2020vision": 636,
  "jokeglasses2020vision": 637,
  "3dglasses2020vision": 638,
  "viewfinder2020vision": 639,
  "vrgoggles2020vision": 640,
  "jewelerloupe2020vision": 641,
  "jewelerloupe2020glasses": 641,
  "aviator2020vision": 642,
  "aviators2020vision": 642,
  "charge": 643,
  "redapple": 644,
  "cherryblossom": 645,
  "flamingarrow": 646,
  "trident": 647,
  "lifebuoy": 648,
  "peach": 649,
  "pear": 650,
  "cucumber": 651,
  "friedegg": 652,
  "pufferfish": 653,
  "rice": 654,
  "roe": 655,
  "salmon": 656,
  "nori": 657,
  "prawn": 658,
  "tuna": 659,
  "sushimasterneko": 660,
  "sushimasterkappa": 661,
  "sushimasteryurei": 662,
  "babynarwhal": 663,
  "babypenguin": 664,
  "babycrab": 665,
  "sealpup": 666,
  "babyshark": 667,
  "switzerlandglobalgrub": 668,
  "australiaglobalgrub": 669,
  "chinaglobalgrub": 670,
  "franceglobalgrub": 671,
  "greeceglobalgrub": 672,
  "japanglobalgrub": 673,
  "thailandglobalgrub": 674,
  "mexicoglobalgrub": 675,
  "koreaglobalgrub": 676,
  "swedenglobalgrub": 677,
  "italyglobalgrub": 678,
  "usaglobalgrub": 679,
  "pakistanglobalgrub": 680,
  "ukraineglobalgrub": 681,
  "spainglobalgrub": 682,
  "montenegroglobalgrub": 683,
  "indiaglobalgrub": 684,
  "portugalglobalgrub": 685,
  "philippinesglobalgrub": 686,
  "rootrunnerboomerang": 687,
  "countrycrawlerboomerang": 688,
  "greatdividingboomerang": 689,
  "partingseaboomerang": 690,
  "sunsetterboomerang": 691,
  "coralcatcherboomerang": 692,
  "hzeewellstimemachine": 693,
  "zeeloreontimetraveler": 694,
  "tardytimetraveler": 695,
  "thereturn": 696,
  "rainbowtrail": 697,
  "redzed": 698,
  "orangezed": 699,
  "yellowzed": 700,
  "greenzed": 701,
  "bluezed": 702,
  "indigozed": 703,
  "violetzed": 704,
  "louroll": 705,
  "babybunny": 706,
  "babychick": 707,
  "babyfawn": 708,
  "babylamb": 709,
  "babytiger": 710,
  "piratejoke": 711,
  "librarianjoke": 712,
  "bisonjoke": 713,
  "fishyjoke": 714,
  "dadjoke": 715,
  "grapejoke": 716,
  "chillyjoke": 717,
  "cyclistjoke": 718,
  "ninjajoke": 719,
  "unicornjoke": 720,
  "staysafe": 721,
  "deliveryhero": 722,
  "educationhero": 723,
  "groceryhero": 724,
  "healthcarehero": 725,
  "firstresponderhero": 726,
  "deliveryheromask": 727,
  "educationheromask": 728,
  "groceryheromask": 729,
  "healthheromask": 730,
  "firstresponderheromask": 731,
  "vietnamglobalgrub": 732,
  "kringlescowboyhat": 733,
  "lonestartreetopper": 734,
  "silverspurs": 735,
  "christmascactus": 736,
  "bootscootinstocking": 737,
  "stateshapedornament": 738,
  "canofakesnow": 739,
  "festivefootball": 740,
  "gingerbreadbarn": 741,
  "bluebonnetmistletoe": 742,
  "santassaddle": 743,
  "nacogdochesnutcracker": 744,
  "shurikenninjabreadman": 745,
  "saininjabreadman": 746,
  "nunchuckninjabreadman": 747,
  "katananinjabreadman": 748,
  "mhqlue": 749,
  "universityprofessorcorn": 750,
  "misterzee": 751,
  "mademoiselleeventa": 752,
  "generalgreene": 753,
  "banhammercard": 754,
  "externalbatterycard": 755,
  "unicornhorncard": 756,
  "globecard": 757,
  "theproductionroom": 758,
  "thevideocaststudio": 759,
  "themunzeemuseum": 760,
  "origamicrane": 761,
  "origamilily": 762,
  "origamiboat": 763,
  "origamibutterfly": 764,
  "theczeeosoffice": 765,
  "frankensteinshand": 766,
  "mummyhand": 767,
  "werewolfpaw": 768,
  "knightshelmet2019": 769,
  "knightsrightgauntlet2019": 770,
  "knightsleftgauntlet2019": 771,
  "knightsbreastplate2019": 772,
  "knightsleftboot2019": 773,
  "knightsrightboot2019": 774,
  "chinaprcoupedu": 775,
  "australiacoupedu": 776,
  "brazilcoupedu": 777,
  "argentinacoupedu": 778,
  "englandcoupedu": 779,
  "camerooncoupedu": 780,
  "canadacoupedu": 781,
  "chilecoupedu": 782,
  "magic8ballaskrob": 783,
  "magic8ballblamescott": 784,
  "magic8ballnope": 785,
  "magic8ballthisisfine": 786,
  "magic8ball1000hours": 787,
  "flatshuttle": 788,
  "flatflybyrob": 789,
  "flatflybymatt": 790,
  "flatflybylou": 791,
  "flatflybyhammock": 792,
  "8mate": 793,
  "shesaidyesphysical": 794,
  "shesaidyesvirtual": 795,
  "whitetooth2019": 796,
  "goldtooth2019": 797,
  "diamondtooth2019": 798,
  "magic8ballu00bf": 799,
  "magic8ballexpecttheunexpected": 800,
  "magic8ballgrowthemap": 801,
  "clowncar2018": 802,
  "worldphotoday2018": 803,
  "flyingpig": 804,
  "americanbacon": 805,
  "internationalbacon": 806,
  "cargoship": 807,
  "treasureship": 808,
  "ghostship": 809,
  "zombieoutbreak2018": 810,
  "2011munzeelogo": 811,
  "2013munzeelogo": 812,
  "2014munzeelogo": 813,
  "2015munzeelogo": 814,
  "2018munzeelogo": 815,
  "flatsanta2018": 816,
  "dasherreindeer2018": 817,
  "dancerreindeer2018": 818,
  "prancerreindeer2018": 819,
  "vixenreindeer2018": 820,
  "cometreindeer2018": 821,
  "cupidreindeer2018": 822,
  "donnerreindeer2018": 823,
  "blitzenreindeer2018": 824,
  "rudolphreindeer2018": 825,
  "roverreindeer2018": 826,
  "heavenlyhammock": 827,
  "yellowthrowbackcandyheart": 828,
  "greenthrowbackcandyheart": 829,
  "orangethrowbackcandyheart": 830,
  "redthrowbackcandyheart": 831,
  "wallaweefella": 832,
  "flatfish": 833,
  "redherring": 834,
  "bouncingbenson": 835,
  "floatingbenson": 836,
  "whiteegg": 837,
  "blueegg": 838,
  "redegg": 839,
  "yellowegg": 840,
  "hatchedwhiteegg": 841,
  "hatchedblueegg": 842,
  "hatchedredegg": 843,
  "hatchedyellowegg": 844,
  "alienegg": 845,
  "alienpotato": 846,
  "ufo": 847,
  "ufovirtual": 848,
  "pinpointsvirtual": 849,
  "pinpointsphysical": 850,
  "scavengerhuntdaycompass": 851,
  "scavengerhuntdaytelescope": 852,
  "scavengerhuntdaymagnifyingglass": 853,
  "scavengerhuntdayshovel": 854,
  "francecoupedu": 855,
  "nigeriacoupedu": 856,
  "norwaycoupedu": 857,
  "southkoreacoupedu": 858,
  "germanycoupedu": 859,
  "southafricacoupedu": 860,
  "spaincoupedu": 861,
  "italycoupedu": 862,
  "jamaicacoupedu": 863,
  "japancoupedu": 864,
  "scotlandcoupedu": 865,
  "netherlandscoupedu": 866,
  "newzealandcoupedu": 867,
  "swedencoupedu": 868,
  "thailandcoupedu": 869,
  "unitedstatescoupedu": 870,
  "potogold": 871,
  "eventzee": 872,
  "fromspacecoastwithlove": 873,
  "wisconsin2015": 874,
  "loveintheair": 875,
  "texasindependence": 876,
  "mmiv": 877,
  "mmivfridaynight": 878,
  "amsterdam2015": 879,
  "celle2015": 880,
  "heartsindc": 881,
  "spacecoastpiday": 882,
  "spartanburghunt": 883,
  "eaglelakeevent": 884,
  "secondbattleoffranklin": 885,
  "springfling2015": 886,
  "sillyman": 887,
  "iaf2015": 888,
  "bartonblues2015": 889,
  "deocaching2015": 890,
  "swfl2015": 891,
  "londonrobbed": 892,
  "londontiming": 893,
  "munzee4acure": 894,
  "postrelaychallenge": 895,
  "robinnc2015": 896,
  "minthill2015": 897,
  "danvillecomiccon2015": 898,
  "intercontinentalmunzeemeetandgreet2015": 899,
  "twente2015": 900,
  "mayflowers": 901,
  "greetingsfromflorida2015": 902,
  "weymayday2015": 903,
  "mwmb2015": 904,
  "gwxiii": 905,
  "forgingcommunity2015": 906,
  "crossingoverii": 907,
  "towelday2015": 908,
  "plymouth2015": 909,
  "collegeforkids2015": 910,
  "wisconsinparty2015": 911,
  "happy4thbirthdaypuntagorda": 912,
  "happy4thbirthdaydk": 913,
  "happy4thbirthdayfitchburg": 914,
  "happy4thbirthdayohio": 915,
  "blastintheparkii": 916,
  "happy4thbirthdaync": 917,
  "happy4thbirthdaydebrecen": 918,
  "happy4thbirthdayprague": 919,
  "happy4thbirthdayzwolle": 920,
  "happy4thbirthdayprinceton": 921,
  "happy4thbirthdayberlingrunewald": 922,
  "happy4thbirthdayyorkshire": 923,
  "happy4thbirthdaytasmania": 924,
  "happy4thbirthdaymiami": 925,
  "happy4thbirthdaykalispell": 926,
  "happy4thbirthdaykeysborough": 927,
  "happy4thbirthdaykansascity": 928,
  "4thbirthday": 929,
  "4thbirthdaycaketurtle": 930,
  "4thbirthdaycakechocolate": 931,
  "4thbirthdaycakestrawberry": 932,
  "4thbirthdaycakevanilla": 933,
  "happy4thbirthdayberlinhumboldthain": 934,
  "happy4thbirthdayperth": 935,
  "happy4thbirthdaysydney": 936,
  "happy4thbirthdayshepparton": 937,
  "happy4thbirthdaystuttgart": 938,
  "happy4thbirthdaykent": 939,
  "happy4thbirthdaytidewater": 940,
  "happy4thbirthdayswitzerland": 941,
  "happy4thbirthdaypa": 942,
  "happy4thbirthdaygrafton": 943,
  "3rdeuropeevent": 944,
  "cologne2015day2": 945,
  "socalmunzeecon2015": 946,
  "meetskylar": 947,
  "eagledadandxeniacometoma2015": 948,
  "awalkinthepark2015celle": 949,
  "fl2berlin2015": 950,
  "thedogdaysofsummerinnh2015": 951,
  "rodsribsandmunzees2015": 952,
  "flagcitymunzeefest2015": 953,
  "zombiesatemymunzees2015": 954,
  "westbendmunzeebash2015": 955,
  "meetandeat": 956,
  "summertimeblues2015": 957,
  "2ndannualkalispellevent": 958,
  "hotdogpa2015": 959,
  "stmarysbacon": 960,
  "stmarysegg": 961,
  "ddcardselkevent": 962,
  "dogdaysofsummerinfl2015": 963,
  "tasteofchittering2015": 964,
  "hamptonroadsmultievent2015": 965,
  "awalkinthepark2015": 966,
  "mannheim2015": 967,
  "fridaynightjibby2015": 968,
  "jibbyfest2015": 969,
  "chitteringwildflowerfestival2015": 970,
  "camunzeepizzabash2015": 971,
  "livefreeordie1yearcelebrationuk": 972,
  "livefreeordie1yearcelebrationusa": 973,
  "triplecrown2015": 974,
  "roundthebend2015": 975,
  "whatismunzeemacat": 976,
  "whatismunzeema": 977,
  "arts55thyearanniversary": 978,
  "mhqbash2015": 979,
  "koelnerstammtischv": 980,
  "preukbashbreakfast": 981,
  "mhqbashuk2015": 982,
  "newenglandmunzeers2015": 983,
  "arthursseatmunzfest2015": 984,
  "forgingcommunityinrome2015": 985,
  "thehillsarealive2015": 986,
  "munzspooktackulari": 987,
  "munzspooktackularii": 988,
  "halloweeninspace2015": 989,
  "somemorefun2015": 990,
  "backtothefutureday": 991,
  "munzeeweenii": 992,
  "munztoberrobzombeeevent2015": 993,
  "munzeesandtreatsi": 994,
  "munzeesandtreatsii": 995,
  "drammunzeelunchzee2015": 996,
  "happybirthdaybilly2015": 997,
  "creepybag": 998,
  "frankensteinarm": 999,
  "frankensteinleg": 1000,
  "frankensteinbody": 1001,
  "frankensteinhead": 1002,
  "meetandgreetinworkum2015": 1003,
  "nemunzeemeetandgreet2015": 1004,
  "cookiecrumbles2015": 1005,
  "brooklandsmotorcircuit2015": 1006,
  "spartanburgturkeyhunt2015": 1007,
  "hidudeturns1million": 1008,
  "thereturnoftheminutemen": 1009,
  "kalispellchristmasmunzeeevent": 1010,
  "adickenschristmasatdowntowndisney": 1011,
  "weihnachteninberlin": 1012,
  "cappingthecoastfridaynight": 1013,
  "merrymunzmas2": 1014,
  "abearymunzeechristmas": 1015,
  "santarob": 1016,
  "cappingthecoast2merrittisland": 1017,
  "christmasinthevillage": 1018,
  "froheweihnachtmerrychristmas": 1019,
  "merrymaryland": 1020,
  "nhredneckchristmasfun": 1021,
  "stxmerrychristmas": 1022,
  "bah": 1023,
  "maerchenmarktmunzeemeetinggera": 1024,
  "munzeekaracsonybudapest2015": 1025,
  "shoqagachristmas": 1026,
  "texascraftchristmas": 1027,
  "christmasinrochester": 1028,
  "alabamariverchristmas": 1029,
  "christmasqrackerportland": 1030,
  "deomunzeexmasdebrecen": 1031,
  "drammunzeechrizeemas": 1032,
  "gluehweinimpott": 1033,
  "maooooohhhfudge": 1034,
  "rudolphriverrumble": 1035,
  "christmascookiesonmilk": 1036,
  "12daysofmunzeechristmasi": 1037,
  "12daysofmunzeechristmasii": 1038,
  "sappalotchristmas": 1039,
  "yorkshirechristmasparty": 1040,
  "pachristmasparty": 1041,
  "deckthehalls": 1042,
  "noelinshepparton": 1043,
  "scanclickcache": 1044,
  "xmasincelle": 1045,
  "suncoastchristmascheer": 1046,
  "willthebellsend": 1047,
  "xmasinhannover": 1048,
  "christmasinspartanburg": 1049,
  "acharliebrownchristmas": 1050,
  "christmasinworkum2015": 1051,
  "detstorejuleevent": 1052,
  "snowshoesandflipflops": 1053,
  "christmasinamsterdam2015": 1054,
  "nhcapricornsrule2016": 1055,
  "suncoastii": 1056,
  "averymerryunbirthday2016": 1057,
  "dcmdvaiamfull1000days": 1058,
  "riseandshinefl2016": 1059,
  "nemeetandgreet2016": 1060,
  "stammtischlueneburgjan2016": 1061,
  "txaustraliaday2016": 1062,
  "lasvegasmeetandgreet2016": 1063,
  "australiaday2016": 1064,
  "celebratemunzeefl2016": 1065,
  "haveaheartblooddrive2016": 1066,
  "bemymunzeetine2016": 1067,
  "munzeeloversmeetup2016": 1068,
  "willyoubemine2016": 1069,
  "bythezeeside2016": 1070,
  "leapday2016": 1071,
  "mmcocoabeachgrandopening": 1072,
  "workum2berlin2016": 1073,
  "onemoreday2016": 1074,
  "leapingdudeclanmunzees": 1075,
  "eggzeehuntpraguei": 1076,
  "eggzeehuntpragueii": 1077,
  "eggzeehuntpragueiii": 1078,
  "eggscellentmunzq2016": 1079,
  "celleandtheeasterbunny2016": 1080,
  "beyondthepale2016": 1081,
  "kceastereggstravaganza2016": 1082,
  "alabamariverregioneasterparade": 1083,
  "awalkalongthetrails2016": 1084,
  "kcwakeyouup": 1085,
  "ntxfuzzybicentennial": 1086,
  "tidewatermunzeespdp2016": 1087,
  "doublethefuninlondon2016": 1088,
  "eastereggsinhannover": 1089,
  "hopskipjump": 1090,
  "orimattila2016": 1091,
  "easterinbudapest2016": 1092,
  "sappaloteaster2016": 1093,
  "yorkshireeasterparty2016": 1094,
  "firstdayofspringeggstravaganza": 1095,
  "eastereggcitement2016": 1096,
  "prague2016": 1097,
  "transatlanticeggstravaganzausa": 1098,
  "transatlanticeggstravaganzauk": 1099,
  "suncoastspringfling2016": 1100,
  "joepoollakeevent2016": 1101,
  "hoppingaroundspartanburg2016": 1102,
  "paeastercelebration2016": 1103,
  "deoeaster2016": 1104,
  "paskilinkoping2016": 1105,
  "overcookedham2016": 1106,
  "virtualresort": 1107,
  "virtualresortroom": 1108,
  "sydneyeasterparade2016": 1109,
  "munzeemeetingchemnitz2016": 1110,
  "nemunzeastergames2016": 1111,
  "ncspringfling2016": 1112,
  "malvernegghuntuk2016": 1113,
  "munzeewarriorseaster2016": 1114,
  "dkringstedevent2016": 1115,
  "ntxqrazyunicornpageant2016": 1116,
  "drammunzee2016": 1117,
  "omahaspringfling2016": 1118,
  "norcaleaster2016": 1119,
  "huntforthefranklinbeast2016": 1120,
  "dkeaster2016": 1121,
  "franklineveningcelebration2016": 1122,
  "exploringmiddletennessee2016": 1123,
  "sheppartoneasteregghunt2016": 1124,
  "welcometofranklin2016": 1125,
  "easterlakecelebration2016": 1126,
  "eastereventamsterdam2016": 1127,
  "springfling2": 1128,
  "wisconsineasterparade2016": 1129,
  "wildernesseaster2016": 1130,
  "eastermunzeggdarlington2016": 1131,
  "hoponovertothebeach2016": 1132,
  "raindrop": 1133,
  "munzeenationassembly": 1134,
  "foodtruckfandango": 1135,
  "munzeemadnessv": 1136,
  "easterbunny": 1137,
  "2ndannualmunzee4acure": 1138,
  "melbourneaustraliawelcomesflorida2016": 1139,
  "blastinthepark3": 1140,
  "maythe4th2016": 1141,
  "discoverminthill2": 1142,
  "munzfitprague2016": 1143,
  "perthwelcomesfloridadownunder": 1144,
  "maymunzeemeetgreetcapeatatbarberscrossing": 1145,
  "mikescelebrationoflife": 1146,
  "munzfitcellei": 1147,
  "munzfitcelleii": 1148,
  "stammtischcelle": 1149,
  "meetatthemoat": 1150,
  "511whoyougonnacall": 1151,
  "helluntainhulinat": 1152,
  "dkmunzeepaafur": 1153,
  "munzfitlondon": 1154,
  "mwmbfridaynighthangout": 1155,
  "lommelevent2016belgium": 1156,
  "midwestmunzeebash16": 1157,
  "voteforgof": 1158,
  "munzeemarketplacecbribboncutting": 1159,
  "grandopeningtake3": 1160,
  "getoutside2016": 1161,
  "virginia2016": 1162,
  "onthebiketrail": 1163,
  "robicorn": 1164,
  "gwxiv": 1165,
  "5thbirthday": 1166,
  "5thbirthdaygift": 1167,
  "geowoodstock14er": 1168,
  "weare5": 1169,
  "milehighmunzbrews": 1170,
  "rockysunrise": 1171,
  "faretheewell": 1172,
  "hmlistenkynnistys": 1173,
  "milehighmischief": 1174,
  "munzee5zlinapbirthdaypartybudapest": 1175,
  "aberlinmunztersbirthdayparty": 1176,
  "canadadaymunzeeindependencedaybirthdaybash": 1177,
  "dkringstedhalvrundfdselsdag": 1178,
  "iapartyonthebanks": 1179,
  "munzee5thbirthdayinplymouth": 1180,
  "nhbirthdayinthepark": 1181,
  "orimattilamunzeebirthdayparty2016": 1182,
  "rnkmmiv5thbirthday": 1183,
  "happyfifthbirthday": 1184,
  "gratulerermed5rsdagen": 1185,
  "5thbirthdaycelebrationsinshepparton": 1186,
  "5thbirthdaybonn": 1187,
  "wibirthdayluau": 1188,
  "munzees5thbirthdayeventoc": 1189,
  "birthdayinthepark": 1190,
  "xmarksthespot": 1191,
  "dkmunzee5thbirthdaydinner": 1192,
  "hannoverbirthdayparty": 1193,
  "hannoverbirthdaypartyafternoon": 1194,
  "munzees5thbirthdayinleeds": 1195,
  "dkmunzee5thbirthday": 1196,
  "london5thbirthdayevent": 1197,
  "akickstart": 1198,
  "cedarrapidsbirthdaybash": 1199,
  "berkshiremunzeebirthdaybash": 1200,
  "alabamamunzee5thbirthday": 1201,
  "anuncommonbirthday": 1202,
  "melbournesmidwintermunzfest2": 1203,
  "birthdaybashbydrvclan": 1204,
  "kent5thbirthdaybash": 1205,
  "pahappybirthday": 1206,
  "flmunzeebirthdaycelebration": 1207,
  "birthdayextravaganza20": 1208,
  "celebratingthetoledozoo": 1209,
  "explorefaribaultmn": 1210,
  "kansascitymunzeebirthdaybash2016": 1211,
  "sydneydinner": 1212,
  "warriorsbirthday": 1213,
  "theweirdhattersteaparty": 1214,
  "munzeeturns5sydney2016": 1215,
  "wnybirthdaygathering": 1216,
  "adelaide5thbirthdayevent": 1217,
  "ncdrive95": 1218,
  "halberstadtm5": 1219,
  "madisonwi2016": 1220,
  "pinellasfatcatbirthdaybash": 1221,
  "spartanburgcelebratesmunzees5th": 1222,
  "stammtischhalberstadt": 1223,
  "floridasflipfloptothebeach": 1224,
  "bestfest2016": 1225,
  "heyheywerethemunzeers": 1226,
  "1stsocialsouthend": 1227,
  "dogdaysofsummerii": 1228,
  "markcase": 1229,
  "questingforquesting4": 1230,
  "coexistingonsanibelisland17yearcelebration": 1231,
  "lilygrimaldisgardenparty": 1232,
  "backtoschool2016": 1233,
  "munzeeinghamptonroads2016": 1234,
  "labordayatthebeach": 1235,
  "californiaadmissiondaycelebration": 1236,
  "iacedarrapidsclanrivalryday": 1237,
  "kidneyhealthresearchwalk2016": 1238,
  "worcesterpoodleparty": 1239,
  "jibbyfridaynightjibbyjibbyfest2016": 1240,
  "jibbyjibbyfest2016euro": 1241,
  "jibbyjibbyjibbyfest2016": 1242,
  "munzcamp2016waypoint1": 1243,
  "munzcamp2016waypoint2": 1244,
  "jibbybreakfastjibbyjibbyfest2016date20": 1245,
  "lincolns1stevent": 1246,
  "deutschlandfeiert": 1247,
  "gothenburggtaexplosion2016": 1248,
  "amunzeegemevent": 1249,
  "snaillakeparkfallinto": 1250,
  "greermunzeehunt": 1251,
  "netrickzeeortreatzeespooktacularevent": 1252,
  "stlouismegamunzeefest": 1253,
  "northeastgreatpumpkinbash": 1254,
  "flsuncoastspooktacular": 1255,
  "munzeeweeniii": 1256,
  "funinthesun": 1257,
  "1stannualmunztersmash": 1258,
  "frightnight": 1259,
  "mchenrymunzeemeetup": 1260,
  "nehuntfortheheadlesshorsezee": 1261,
  "meerkatmunzketeers": 1262,
  "bewitchingburnley": 1263,
  "hstreetnortheastisscary": 1264,
  "hanshotfirsthalloweenbrewevent": 1265,
  "derdemeetengreet": 1266,
  "lonestarcoexistroundup": 1267,
  "scottishritemunzeemasters": 1268,
  "remembrance": 1269,
  "capturethefarmingtongemtrail": 1270,
  "thanksgiving2016": 1271,
  "blackfridaycappingthecoast": 1272,
  "2ndalabamariverregionchristmasparty": 1273,
  "africkinfindlaychristmasevent": 1274,
  "campfalalalala": 1275,
  "christmasintheliquidsunshine": 1276,
  "christmasintheemeraldcity": 1277,
  "dkdetstorejuleevent2016": 1278,
  "findlayssmashinggreatchristmasevent": 1279,
  "goodnighttoallfindlaythanksyou": 1280,
  "nhfrostzeethemunzman": 1281,
  "plymouthchristmasevent": 1282,
  "chemnitzerweihnachtsmarkt2016": 1283,
  "adelaidechristmasevent": 1284,
  "christmasinturku": 1285,
  "fltitusvillemunzeewarriorsridingthexmasrocket": 1286,
  "leyduinevent": 1287,
  "spiraltrolletsjule": 1288,
  "xmas2016dortmund": 1289,
  "ymhchristmasparty": 1290,
  "firework2016": 1291,
  "ignitedfirework2016": 1292,
  "merrymunzmas3": 1293,
  "achristmasdinnerinshepparton": 1294,
  "averymerrymunzeechristmas": 1295,
  "awnychristmasmunzparty": 1296,
  "chilichristmasbash": 1297,
  "christmasinprague2016": 1298,
  "christmasinshepparton2016": 1299,
  "christmasmunzeepartyinappletonwi": 1300,
  "dksealandhappyxmas": 1301,
  "fatherchristmasinfakenham": 1302,
  "anorthcarolinachristmas": 1303,
  "berlinerweihnachtsevent": 1304,
  "christmasintexas": 1305,
  "helsinkixmasparty": 1306,
  "nhcookiesonmilk2": 1307,
  "alightsaberroguechrismas": 1308,
  "bluemunzeewithoutyou": 1309,
  "deoxmas2016": 1310,
  "kansascitysletitsnow": 1311,
  "santaontheloo": 1312,
  "santassunshineshingding": 1313,
  "budapestmunzeexmaskaracsony2016": 1314,
  "leedschristmasbash": 1315,
  "newhampshirechristmas": 1316,
  "adudeclanchristmas": 1317,
  "kansascityscandycanelane": 1318,
  "acharliebrownchristmasevent2016": 1319,
  "twilightxmasinsa": 1320,
  "christmasinpa2016": 1321,
  "londonchristmas2016": 1322,
  "welcome2017drachenfels": 1323,
  "frankbroughtonsbigbirthdayblowoutbonanza": 1324,
  "flsuncoasteventiii": 1325,
  "flsuncoastpiratefeast": 1326,
  "suncoastmunzeeahoy": 1327,
  "picnicinthepark2017": 1328,
  "flsuncoastsunrise": 1329,
  "munzeevictoriadinner": 1330,
  "australiaday2017": 1331,
  "agatheringofthefederation": 1332,
  "txwhiteunicorn": 1333,
  "westernaustraliadayinsheppzee": 1334,
  "groundhogday2017": 1335,
  "nzsouthislandmeetmhq": 1336,
  "flkiwanisislandshoppingday": 1337,
  "mhqinnz": 1338,
  "florangeyougladyousawaflagwavingmanate": 1339,
  "1stwollukevent": 1340,
  "mostlvalentineblooddrive": 1341,
  "boxofchocolates2017": 1342,
  "coconutchocolate2017": 1343,
  "cherrychocolate2017": 1344,
  "darkchocolate2017": 1345,
  "zeeopsspecial": 1346,
  "munzeeloveinfortmyersfl": 1347,
  "munzeeloveisintheair": 1348,
  "veteransmemorialparkcelebration": 1349,
  "flmunzeelighthousepark": 1350,
  "foodtruckfantastico": 1351,
  "breakfastbeforethemadness": 1352,
  "munzeemadness6": 1353,
  "munzeemadnessvidinnerparty": 1354,
  "theprankster": 1355,
  "luckyleprechaunevent2017": 1356,
  "spacecoastcomestotylertx": 1357,
  "bestfest2": 1358,
  "teaparty2017": 1359,
  "fllakemanateaparty2017": 1360,
  "manateeastercelebration2017": 1361,
  "bostonteaparty2017": 1362,
  "ageneseoteapartywhereeveryonehascoffee": 1363,
  "il1stannualcuriositeaparty": 1364,
  "nycaffeineoverload": 1365,
  "alynwaterseastereggcitment": 1366,
  "afloridaeasterluncheon2017": 1367,
  "bidefords1steventitsteatime": 1368,
  "easterinoz2017": 1369,
  "eggstraspecialmarylandmunzeeeasterevent": 1370,
  "houstonwehaveateaparty": 1371,
  "munzeebytheseenz": 1372,
  "munzeehsvtbudapest": 1373,
  "springtimeatthezoo2017": 1374,
  "stuttgartteatimeinhohenheim": 1375,
  "eastertrollhunt": 1376,
  "mahoppyeasteratindianhill": 1377,
  "dkpskeiaarhus": 1378,
  "njbilbyevent": 1379,
  "hoppingtimeinthecarolinas": 1380,
  "adelaideeasterevent2017": 1381,
  "ahappymunzeeastermmxvii": 1382,
  "teapartyinhelsinki2017": 1383,
  "teapartyeventinturku": 1384,
  "flsuncoasteggstravaganza2017": 1385,
  "pershoresmeltingeggs": 1386,
  "orimattilanpsiinen": 1387,
  "hunterseastermunzeebash": 1388,
  "timeshare": 1390,
  "alacatfisheaster": 1391,
  "moshamrocksandeaster": 1392,
  "fridaynightteaser": 1393,
  "1stofthe2ndannualalabamaeasterevents": 1394,
  "2munzeehsvt": 1395,
  "2ndofthe2ndannualalriverregionteaparties": 1396,
  "3rdofthe2ndannualalabamaeasterevents": 1397,
  "amanfangwardasei": 1398,
  "froghollow": 1399,
  "southerncaliforniaaprilteapartyevent": 1400,
  "millsparkeaster": 1401,
  "stgeorgeseasterparty": 1402,
  "teapartyleyduin": 1403,
  "moviesmonstersand1": 1404,
  "rackheathspinwheelteaparty": 1405,
  "ncchallengesinthepinesevent1": 1406,
  "ncchallengesinthepinesevent2": 1407,
  "ncchallengesinthepinesevent3": 1408,
  "aslinkyeaster2017": 1409,
  "aftereastermeetandgreet": 1410,
  "easterinshepparton": 1411,
  "ntxtexasteaparty": 1412,
  "springinthearizonadesert": 1413,
  "codnorcasinobankholidayprizebonanza": 1414,
  "helsinkie1ew": 1415,
  "frankfurtlion": 1416,
  "munzeemaymayheminleeds": 1417,
  "worldturtleday2017": 1418,
  "2etwenteeventthenetherlands": 1419,
  "orangepark": 1420,
  "amaymunzeemeetup": 1421,
  "munzeemeetgreetinashevillenc": 1422,
  "coexist15": 1423,
  "malvernglacierevent": 1424,
  "mwmb17fridaynighthangout": 1425,
  "getoutdoorsbaytown": 1426,
  "mwmb2017": 1427,
  "spectacular6thbirthdayspecial": 1428,
  "6thbirthdaybam": 1429,
  "6thbirthdaypow": 1430,
  "6thbirthdaybang": 1431,
  "gafolkstonfunnel": 1432,
  "holmenkollbakken2017": 1433,
  "maeagledadandxeniacometomathesequel": 1434,
  "sunnysouthport": 1435,
  "suissesummerevent": 1436,
  "6thbirthdaysuperrob": 1437,
  "6thanniversary": 1438,
  "appletonsprebirthdaymeetandgreet": 1439,
  "cedarrapidsbirthdaybashinthepark": 1440,
  "cedarrapidsasecondannualbirthdaybash": 1441,
  "cedarrapidsbirthdaybashatthelake": 1442,
  "letsluaumunzees6thbirthday": 1443,
  "westcovinas1stevent": 1444,
  "alrr6thbirthdaycelebration": 1445,
  "munzeemeetsowlbirthdaybash14": 1446,
  "munzeemeetsowlbirthdaybash24": 1447,
  "dogdaysofsummeriii": 1448,
  "melbournesmidwintermunzday3": 1449,
  "munzeepostbirthdaybash": 1450,
  "sixyearsplusaretirement": 1451,
  "ncanothersixyearevent": 1452,
  "6ofsunstroke": 1453,
  "barnstaplebirthdaybash": 1454,
  "birthdaybashboardgames": 1455,
  "munzeemeetsowlbirthdaybash34": 1456,
  "munzeemeetsowlbirthdaybash44": 1457,
  "mdmunzee6thbirthdaycelebration": 1458,
  "ymhbirthdayparty": 1459,
  "munzee6thbd": 1460,
  "zpeeralenbirthdayevent": 1461,
  "mabirthdaybash2017": 1462,
  "birminghamalbirthdaypartycoexist": 1463,
  "mhqbirthdaybash2017": 1464,
  "munzeen6vuotissynttritturussa": 1465,
  "dkbirthdaybbqparty": 1466,
  "dkmunzee6thbirthday": 1467,
  "hellsinkimunzfun": 1468,
  "iadesmoinesbirthdaybash": 1469,
  "munzee6thbirthdaychristmasinjuly": 1470,
  "munzeeturns6inthelandofthek1w1": 1471,
  "pubcrawlvirginiabeachedition": 1472,
  "suncoastpartytime2017": 1473,
  "brockenhurstvillagetopazmunzeebirthdayevent": 1474,
  "celebrating6inbattleground": 1475,
  "munzeeinthemountains6thbirthdaybash": 1476,
  "munzees6thbirthdaypartyatthepark": 1477,
  "6thbirthdaycelebrationsintatura": 1478,
  "ohhappybirthdayinwauseon": 1479,
  "wichitabirthdaybash2017": 1480,
  "6thbirthdayinwellington": 1481,
  "budapest2017m6": 1482,
  "letspartylikea6yearold": 1483,
  "scasuperduperultrabirthdaycelebration": 1484,
  "spejderneslejr2017": 1485,
  "battleoftewkesbury": 1486,
  "mismalltowneventvicksburgmichigan": 1487,
  "mwmbmuncie": 1488,
  "kansascitybirthdaybash2017": 1489,
  "6yearoldbirthdaybash": 1490,
  "amunzeebirthdaycelebration": 1491,
  "happybirthday": 1761,
  "munzee6szlinap": 1493,
  "munzees6thinonkaparinga": 1494,
  "flspacecoastbirthdaycelebration": 1495,
  "secretagentbillsbigride": 1496,
  "wimunzeeinregnerpark": 1497,
  "vielonkesjljell": 1498,
  "wispacecoastvisitsappleton": 1499,
  "internationalleftiesday2017": 1500,
  "lefthandedthumbsup": 1501,
  "mnspacecoastvisitsbloomington": 1502,
  "iaspacecoastvisitscedarrapids": 1503,
  "almostblackedout": 1504,
  "thegreatamericansolarzeeseclipse": 1505,
  "greerhuntfortheaceasmalltownevent": 1506,
  "greermunzeehuntii": 1507,
  "solskinsenssummerevent": 1508,
  "vahamptonroadsencoremunzeeevent": 1509,
  "15thgeocachinghamptonroadspicnicmunz": 1510,
  "girlscoutgetfittrailkickoff": 1511,
  "getfittrailcooldown": 1512,
  "firstlimboevent": 1513,
  "metrovancouversummermunzbash": 1514,
  "pnwmunzeebash": 1515,
  "lasmalltowneventslidell": 1516,
  "flsmalltowneventauburndale": 1517,
  "therichardsradclifferamble": 1518,
  "grboexplosion1": 1519,
  "mhqmunzfit2017": 1520,
  "grboexplosion2017": 1521,
  "mhqbash4deuceswild": 1522,
  "uksdhmegaweekenderferndown": 1523,
  "uksdhmegaweekendersouthampton": 1524,
  "wallabashatmhq": 1525,
  "lincolnwinnersenclosureevent": 1526,
  "flfrightfulfeteonthesuncoast": 1527,
  "munzfit20berlin": 1528,
  "flsmalltowntupperwareparty": 1529,
  "mamunzfitlakeparkloop": 1530,
  "marunfromjasonmunzfit": 1531,
  "amunzoweenevent": 1532,
  "munzfit20cologne": 1533,
  "tourdecuredfw": 1534,
  "flmunzeeinparadisesanibelisland": 1535,
  "aspooktacularkchalloween": 1536,
  "kansascitysghoulishlastcall": 1537,
  "munzeeween2017": 1538,
  "2ndannualmunztersmash": 1539,
  "monstermunzeemash": 1540,
  "nhleafpeepingmunzeestyle": 1541,
  "bewitchingthebee": 1542,
  "nightoftheliving": 1543,
  "somethingwickedthiswaymunzees": 1544,
  "munzeesalutesveterans": 1545,
  "meetgreetkampen": 1546,
  "worlddiabetesday2017": 1547,
  "suomi100finland100years": 1548,
  "munzeecoexistalexandramega2017": 1549,
  "flblackfridayeventspacecoaststyle": 1550,
  "fatherchristmas2017": 1551,
  "leipzighohoho": 1552,
  "thexmasmagicof": 1553,
  "tx2ndannualwhiteunicorn": 1554,
  "santasmunzeeworkshop": 1555,
  "andoverxmasukhampshire": 1556,
  "dkjul2017stjylland": 1557,
  "nhcookiesonmilk3": 1558,
  "txiwantahippopotamusforchristmas": 1559,
  "texasqrazychristmas": 1560,
  "anenaughtyornicexmasmeetandgreet": 1561,
  "alabamachristmasgathering2017": 1562,
  "budapestimunzeekarcsony2017": 1563,
  "christmasincedarrapids2017": 1564,
  "christmasinfaversham": 1565,
  "christmasinshepparton2017": 1566,
  "clancreedchristmascatchup": 1567,
  "gettingchristmaszee": 1568,
  "marylandmunzeechristmas2017": 1569,
  "berlinermunzeeweihnacht": 1570,
  "carolinachristmaschallenges2017": 1571,
  "christmasinconnecticut2017": 1572,
  "darmstdterweihnachtzeevent2017": 1573,
  "helsinkixmaspartyii": 1574,
  "rainychristmasinthepnw": 1575,
  "swisschristmaseventzeedec12th2017": 1576,
  "christmas2017snowflake": 1577,
  "christmas2017sun": 1578,
  "amerrycurlingchristmasinchaska": 1579,
  "feliznavidad": 1580,
  "goudsestroopwaffelchristmasevent2017": 1581,
  "itsasummermunzeechristmas": 1582,
  "kansascitycoffeedonutsinthepark": 1583,
  "christmasintheemeraldcity2017": 1584,
  "acharliebrownchristmas2017": 1585,
  "hsmmunzeechristmas": 1586,
  "leedschristmasparty2017": 1587,
  "pickledforxmaswithmrsherbert": 1588,
  "adelaidechristmasevent2017": 1589,
  "crazycornychristmas": 1590,
  "merrymunzmasiv": 1591,
  "merrychristmas2017inincheon": 1592,
  "christmasinthecarolinas2017": 1593,
  "toochickentoplungemunzeeeventzeeevent": 1594,
  "homefortheholidays2017": 1595,
  "christmas2017florida": 1596,
  "thankyoufromlouise2018": 1597,
  "thankyoufromrob2018": 1598,
  "thankyoufrommatt2018": 1599,
  "flsuncoastivbeachparty": 1600,
  "flsuncoastivwelcome": 1601,
  "suncoastivevening": 1602,
  "suncoastivmainevent": 1603,
  "flhappynewyearpart2": 1604,
  "alabamathanksflorida": 1605,
  "flhappynewyearpart1": 1606,
  "dinnerwiththesnowbirdfriends": 1607,
  "australiaday2018": 1608,
  "australiadayinperth": 1609,
  "heartwrangler1": 1610,
  "heartwrangler2": 1611,
  "heartcapper1": 1612,
  "heartcapper2": 1613,
  "picnicinthepark2018": 1614,
  "gafolkstonfunnelfun": 1615,
  "mm7fridaynightgettogether": 1616,
  "behappyfollowthesun": 1617,
  "behappyhaveaball": 1618,
  "flbehappyeatdessert": 1619,
  "munzeemadness7": 1620,
  "wallabeemm7dinnerparty": 1621,
  "munzeemadness7earlyrisers": 1622,
  "txspacecoastcomestodenton": 1623,
  "gogreen2018": 1624,
  "piday2018": 1625,
  "activitiesintheparkiv": 1626,
  "gogreenphoenixtourdecureandzeetour": 1627,
  "sheppzeechoczeeeventsheppartoneasterevent": 1628,
  "stpattyinthedesert": 1629,
  "strikinitrichonstpattysday": 1630,
  "adelaidegoesgreen": 1631,
  "ausfluginsgrnetemplinberlin": 1632,
  "flgogreenonthespacecoast": 1633,
  "gogreeninnorthcarolina": 1634,
  "march2018equinoxevent": 1635,
  "kokomogreeninitiative": 1636,
  "sebringfloridacoexistgogreen": 1637,
  "sowingmunzeeseeds": 1638,
  "lakenonafltourdecure": 1639,
  "nuttynanvisitsprague": 1640,
  "redwoodparkgoesgreen": 1641,
  "goldfevertuesday": 1642,
  "3rdbudapestmunzeeeasterngogreen": 1643,
  "hellsinkieaster2018": 1644,
  "helsinkieaster2018": 1645,
  "foolisheasterevent": 1646,
  "alriverregionkickoffparty": 1647,
  "alriverregion3rdannualeasterbash2": 1648,
  "alriverregion3rdannualeasterbash": 1649,
  "alriverregioneasterbash5": 1650,
  "alabamariverregioneasterevent3wakeupcall": 1651,
  "gogreenchemnitz": 1652,
  "gogreenorgohome": 1653,
  "gogreenturku2018": 1654,
  "hellospring2018": 1655,
  "kansascityssupergreenevent1": 1656,
  "kansascityssupergreenevent2": 1657,
  "pnwgoinggreenin2018": 1658,
  "alriverregionfarewellevent": 1659,
  "gogreennewengland": 1660,
  "noordwijksgogreenevent": 1661,
  "westonsupermunzees": 1662,
  "maskedflatmatt": 1663,
  "meanie": 1664,
  "gogreenmlndal": 1665,
  "marylandgoesgreenwith": 1666,
  "motorcitygoesgreen": 1667,
  "munzeemeetsowlosterevent": 1668,
  "gogreeninjordan": 1669,
  "lostrivermunzeeraid": 1670,
  "scgogreenontaxday": 1671,
  "spacecoastcomestonebraska": 1672,
  "supergreeninkc": 1673,
  "2ndannualcuriositeaparty": 1674,
  "celebratingearthdayinetx": 1675,
  "litzenberg": 1676,
  "frankfurtplanespottingsundaygreenevent": 1677,
  "gogreenwithmunzeecitoevent": 1678,
  "yorkshiregogreenevent": 1679,
  "lgasmaythefourthbewithlou": 1680,
  "maythefourthbewithyoustarwarsday": 1681,
  "seattletourdecure": 1682,
  "lgasloveouruniqueinternationalsunnyevents": 1683,
  "munzeemania2018mainevent": 1684,
  "munzeemania2018pizzaparty": 1685,
  "munzeemania2018mothersdaycelebration": 1686,
  "towelday2018": 1687,
  "hitchhiker2018": 1688,
  "lgasletsgoandscan": 1689,
  "lgasladylondonappreciation": 1690,
  "thekingqueenvisitkansascity": 1691,
  "lgassalisburyuk": 1692,
  "nyalleganybearevent": 1693,
  "rosemarybuchananmemorialevent": 1694,
  "munzeewoodstockcincinnati": 1695,
  "gw2018munzeemeetgreet": 1696,
  "kysmalltowneventflorence": 1697,
  "beccleswherrymunzeeevent": 1698,
  "mwmb2018fridaynightnatureevent": 1699,
  "mwmb2018": 1700,
  "cobrayogapose": 1701,
  "downwarddogyogapose": 1702,
  "lotusyogapose": 1703,
  "warrioriiyogapose": 1704,
  "sunshineinvilnius": 1705,
  "munzeesoul": 1706,
  "birthdaycircus2018": 1707,
  "gemtlichergrillevent": 1708,
  "berlinerm7geburtstagsevent": 1709,
  "flhappybirthdaymunzeespacecoaststyle": 1710,
  "happy7thbirthday": 1711,
  "mime2018": 1712,
  "trampclown2018": 1713,
  "partyclown2018": 1714,
  "harlequinclown2018": 1715,
  "rodeoclown2018": 1716,
  "scaryclown2018": 1717,
  "sadclown2018": 1718,
  "hellsinkimunzfunii": 1719,
  "stuttgart2018schwabenstreichi": 1721,
  "cedarrapidsgoodmorningbirthdayparty": 1722,
  "3rdannualcedarrapidsmunzeebirthdaybash": 1723,
  "7thbirthdayinsheppzee": 1724,
  "alriverregionsscirquedumunz7thbirthday": 1725,
  "bowlrsbirthday2": 1726,
  "stuttgart2018schwabenstreichii": 1727,
  "stuttgart2018schwabenstreichiii": 1728,
  "7thbirthdayevent": 1729,
  "stuttgart2018schwabenstreichiv": 1730,
  "stuttgart2018schwabenstreichv": 1731,
  "munzeefreakshowbirthdaybirminghamalabama": 1732,
  "pathisbearisgettingold": 1733,
  "cirquedumunzmackay": 1734,
  "cirquedu": 1735,
  "cirquedustoutspectacular": 1736,
  "dogdaysofsummerunderthebigtop": 1737,
  "m7littlebdayindd": 1738,
  "mhqunderthebigtop7thbirthdaycelebration": 1739,
  "manzeonnittelee7vuotiasta": 1740,
  "munzees7thbirthdayinyorkshire": 1741,
  "munzeebirthdayinpraha": 1742,
  "withe3rdannualmunzeebirthdayluau": 1743,
  "adelaidecirquedumunzbirthdayevent": 1744,
  "fthqcirquedumunz7thbirthdaycelebration": 1745,
  "helpsaveourbeesevent": 1746,
  "nrnberg2018m7": 1747,
  "magicallymarvelousmidwaymunzeemixer": 1748,
  "pre3rdannualmunzeebirthday": 1749,
  "sitsipand": 1750,
  "southsoundsummerevent": 1751,
  "birthdayboardgamebash": 1752,
  "dk7thbirthdayeventevening": 1753,
  "munzeedjursland4": 1754,
  "ticketsplease": 1755,
  "munzeeturns7aminneapoliscelebration": 1756,
  "munzeeturns7asaintpaulcelebration": 1757,
  "7thmunzeebirthday7munzeeszlinap": 1758,
  "cirquedulitzenberg": 1759,
  "goingoutwithabanginkc": 1760,
  "marylandcelebratesmunzees7thbirthday": 1762,
  "munzeebirthdayinri": 1763,
  "ohsmalltowneventwauseonoh": 1764,
  "richmondparkbirthdayevent": 1765,
  "sawuontheaveatthe7th": 1766,
  "celebrate7yearswithrebelgtpatsheetz": 1767,
  "amunzeemeetgreetinwestbend": 1768,
  "anafternoonintheprater": 1769,
  "munzeebash2": 1770,
  "fallintomunzeemassstyle": 1771,
  "2ndannualgreatervancouversummermunzbash": 1772,
  "culturelehoofdstadvaneuropa2018leeuwarden": 1773,
  "autumnwave": 1774,
  "northcarolinamunzeefestivalcarythisyear3": 1775,
  "northcarolinamunzeefestivalcarythisyear2": 1776,
  "northcarolinamunzeefestivalcarythisyear1": 1777,
  "northcarolinamunzeefestivalcarygetaway": 1778,
  "premunzeeeventforthencmunzeefestival": 1779,
  "letshaveakikibirminghamal": 1780,
  "oakmountainpaddlenfloatpicnic": 1781,
  "helloautumn": 1782,
  "wheninrome": 1783,
  "bhamwitcheswarlocksluncheon": 1784,
  "zeecappersearlyhalloweenmeetandgreet": 1785,
  "acedarrapidshalloweencelebration": 1786,
  "arizonamunzeeween": 1787,
  "autumninnewengland": 1788,
  "backalleybroomsticksinbrenham": 1789,
  "boobashintheriverregion2018": 1790,
  "boointheburg": 1791,
  "budapesthalloween": 1792,
  "fallhalloweensocial": 1793,
  "gettingbewitchedinbrenham": 1794,
  "halloweenauffrankensteinsspuren": 1795,
  "munzeeweenchristmasbootique": 1796,
  "spookygothenburg2018": 1797,
  "thehallozeencaterwauling": 1798,
  "booofquinte2018": 1799,
  "ghostlyatbeatonpark": 1800,
  "halloween2018turku": 1801,
  "halloweeninplymouth": 1802,
  "halloweenpartyworkum": 1803,
  "munzeehalloweenparty": 1804,
  "samhaininsouthbourneallhallowseveevent": 1805,
  "thewitchinghour": 1806,
  "swissmainstationhelloweenevent18": 1807,
  "aakkosasema": 1808,
  "filsbirthdayhalloweenevent": 1809,
  "afrighteninglyfuntimeinwaconia": 1810,
  "ncspooktacularboardgames": 1811,
  "ahowlinggoodtimeinkansascity": 1812,
  "amischievouskansascityevent": 1813,
  "anominouskansascityevent": 1814,
  "berlinerhalloweenevent2018": 1815,
  "brandonboo2": 1816,
  "brandonboobash2018": 1817,
  "desmoineshalloweenieroast": 1818,
  "pahalloweeneventinjohnstown": 1819,
  "pumpkinspiceeverythingnice": 1820,
  "sheppzeehalloweenzee": 1821,
  "halloweenmunzeebash": 1822,
  "norderstedtshexenevent": 1823,
  "tivertonshalloween": 1824,
  "lasvegas2018": 1825,
  "ascarydinnerdjursland": 1826,
  "djurslandspookysnack": 1827,
  "njsmalltownstanhope": 1828,
  "hobrohalloweenhorror": 1829,
  "witchwaydoweghoul": 1830,
  "bundoorahalloweenbash": 1831,
  "corraltheghouls": 1832,
  "halloweeninnorthflorida": 1833,
  "happyhallowween": 1834,
  "marylandmunzeemonstermash": 1835,
  "avancouverhalloween": 1836,
  "castingaspellinclitheroe": 1837,
  "helloween": 1838,
  "litzenberghalloweenbash": 1839,
  "spookyaussiemawsonlakesadventures": 1840,
  "byebyebash": 1841,
  "horrorhalloween": 1842,
  "centralohiomonstermash": 1843,
  "mhqhauntedhangout": 1844,
  "mhqwerewolfwalking": 1845,
  "mhqwallaboo": 1846,
  "monstermash": 1847,
  "mhqtrickrtrotrace": 1848,
  "nationalblackcatdaycoexist": 1849,
  "2emeetengreetkampen": 1850,
  "thegreatdorchestergunpowdertreasonandplot": 1851,
  "blackfridaymunzeegettogether": 1852,
  "magdeburgchristmas2018": 1853,
  "christmasinsanibel2018": 1854,
  "scroogedatcentralmarket": 1855,
  "alabamarrchristmas2018": 1856,
  "merrymunzmasv": 1857,
  "xxlmaseventbudapest": 1858,
  "iwantahippopotamusforchristmas2018": 1859,
  "tacosforchristmas2018": 1860,
  "pinellaschristmasevent": 1861,
  "cookiesonmilk2018": 1862,
  "letsgetchristmaszeeagain": 1863,
  "jouluinenturku2018": 1864,
  "goudsestroopwaffelchristmasparty": 1865,
  "downhomegathering": 1866,
  "darmstdterweihnachtzeevent22herrngarten": 1867,
  "darmstdterweihnachtzeevent21rosenhhe": 1868,
  "christmasinthedesert": 1869,
  "budapestmunzeechristmas2018": 1870,
  "acedarrapidschristmas2018": 1871,
  "xmasatlyndhurst": 1872,
  "thenantwitchhunt": 1873,
  "marylandmunzeechristmas2018": 1874,
  "helsinkixmaspartyiii": 1875,
  "berlinerweihnachtsevent2018": 1876,
  "edinamnamunzeechristmas": 1877,
  "findlaynaughtyornicexmasjamboree": 1878,
  "santaiscomingtoappleton": 1879,
  "averysheppzeexmas": 1880,
  "christmasbathwater": 1881,
  "holidayhappiness2018": 1882,
  "melekalikimakafrombirmingham": 1883,
  "christmasinnoarlunga": 1884,
  "christmasintheemeraldcity2018": 1885,
  "christmasinthenw2": 1886,
  "julehyggepgrden": 1887,
  "julestuepgrden": 1888,
  "yorkshirechristmasparty2018": 1889,
  "lisebergxmasevent": 1890,
  "acharliebrownchristmas2018": 1891,
  "2018merrychristmaseventofkorea": 1892,
  "achristmastorememberinthecarolinas": 1893,
  "nationallampoonschristmasvacationinkc": 1894,
  "achristmasstoryinkc": 1895,
  "badsantaiscomingtokansascity": 1896,
  "ohchristmaspalmohchristmaspalm": 1897,
  "weihnachtsstressade": 1898,
  "marylandmistletoemischief": 1899,
  "happynewyear2019spacecoast": 1900,
  "bonvoyageklassickelly": 1901,
  "letthesunshinecommence": 1902,
  "suncoasthello": 1903,
  "suncoastinthepark": 1904,
  "suncoastmorningindadecity": 1905,
  "alunicornwatcherssociety2019": 1906,
  "australiaday2019": 1907,
  "australiaday2019inthewest": 1908,
  "fleaglelakecoexisting": 1909,
  "blastinthepark": 1910,
  "groundhogsdayintexas": 1911,
  "yumaweekendmeetandgreet": 1912,
  "smalltowneventvenicefl": 1913,
  "flcampfireonthelake": 1914,
  "gathedevilwentdowntofolkston": 1915,
  "geobuddiesburgerscoexist": 1916,
  "flhikenseek": 1917,
  "sanantoniotxstpatricksdayearly": 1918,
  "mm8monkzeemadness": 1919,
  "mm8monkzeemadnessdinner": 1920,
  "leavingonajetplanedestinationhawaii": 1921,
  "leavingonajetplanedestinationalaska": 1922,
  "leavingonajetplanetourdecape": 1923,
  "mm8rallydaybreakfast": 1924,
  "mm8rallydaydinner": 1925,
  "mm8stage1": 1926,
  "mm8stage2": 1927,
  "mm8stage3": 1928,
  "mm8stage4": 1929,
  "mm8stage5": 1930,
  "planestrainsandmunzeemobiles": 1931,
  "tothemoon": 1932,
  "txsmalltowneventseguin": 1933,
  "maswingintospring": 1934,
  "polkcountymunzeefrenzee1": 1935,
  "flportofcall": 1936,
  "aprilevent2019": 1937,
  "aprilinalabama2019thursdaynightmeetgreet": 1938,
  "activitiesintheparkcraigmuirlake": 1939,
  "birminghamalabamaaprilfoolslunch": 1940,
  "aprilinalabama2019fridayonmymind": 1941,
  "ncaprilinapex": 1942,
  "aprilinalabama2019gooddaysunshine": 1943,
  "aprilinalabama2019mainevent": 1944,
  "aprilinalabama2019saturdaynight": 1945,
  "budapestibolondoshsvt": 1946,
  "aprilinalabama2019happytrails": 1947,
  "aprilliasysilli": 1948,
  "berlineraprilscherz": 1949,
  "itsatrickawhollyfoolishtrick": 1950,
  "munzeeaprilfoolsworkum": 1951,
  "westonsfoolishemeraldgardens": 1952,
  "vodacomscavengerhunt": 1953,
  "isthesnowgoneyet": 1954,
  "lostmythraidcapturethebigorangetruck": 1955,
  "marylandjokerswild": 1956,
  "onioncreekjamboree": 1957,
  "scaprilfuddsday": 1958,
  "springintothedesert": 1959,
  "tospringornottospringthatisthequestion": 1960,
  "rockthering": 1961,
  "lostmythraid": 1962,
  "hellsinkieasterii": 1963,
  "curiositea32019easterevent": 1964,
  "flhoparoundrotarypark": 1965,
  "prague2019easter": 1966,
  "unicornaprilmadness": 1967,
  "kvibergspskevent": 1968,
  "stopfoolingaroundandhaveadrink": 1969,
  "pnp": 1970,
  "ncaprilfoolevent": 1971,
  "1eventinbasel": 1972,
  "aprilinorlando": 1973,
  "clownzeeventkalslotsruin": 1974,
  "foolingaroundinkc": 1975,
  "pafoolishfunforall": 1976,
  "manevertoolatetobeafool": 1977,
  "munzeemania2019pizzaparty": 1978,
  "maythefourthbewithyou2019starwarsday": 1979,
  "munzeemania2019mainevent": 1980,
  "3etwenteevent2019": 1981,
  "munzeemania2019bagelscoffee": 1982,
  "fortmadisoniaarmedforcesday": 1983,
  "wernerbredebuschvsjamesbond": 1984,
  "allroadsleadtowoodstock": 1985,
  "aspmunzeebash": 1986,
  "insmalltownterrehaute": 1987,
  "motuesdaynightatdennys": 1988,
  "kssmalltowneventwichita": 1989,
  "fortworthrootintootinmunzeeroundup": 1990,
  "2ndplanespottingevent": 1991,
  "ghostbusterskelsterbach": 1992,
  "txcheers": 1993,
  "txlonghornslikechipotletooright": 1994,
  "premunzstock2019": 1995,
  "geowoodstock2019": 1996,
  "mhqopenhousegws19": 1997,
  "geomunzstock2019": 1998,
  "ncgreenvillemunzeewinddown": 1999,
  "8thbirthday": 2000,
  "bonn201912": 2001,
  "bonn201922": 2002,
  "flafathersdaycelebration": 2003,
  "highorelinetrailmeetup": 2004,
  "menudo": 2005,
  "2xthecelebrationbudapest": 2006,
  "backtothefuture80sbirthdaycelebration": 2007,
  "davidjoinsthemillionairesclub": 2008,
  "amunzeepowwow": 2009,
  "berlinerm8geburtstagsevent": 2010,
  "waterworks": 2011,
  "mwmb2019": 2012,
  "mattsmunzeemeetupmhq": 2013,
  "ctdogsinthepark": 2014,
  "munzeesbirthdayinadelaide80sstyle": 2015,
  "crossroadsusa1": 2016,
  "ohafterthebashmunzeeevent": 2017,
  "crossroadsusa2": 2018,
  "somersetciderbashtaunton1": 2019,
  "somersetciderbashtaunton2": 2020,
  "somersetciderbashburnhamonsea": 2021,
  "somersetciderbashhighbridge": 2022,
  "aarhus2019": 2023,
  "bowlrs63rdandmunzees8thbirthday": 2024,
  "dkmunzeemeetsdjurslandbirthdayparty14": 2025,
  "dkmunzeemeetsdjurslandbirthdayparty24": 2026,
  "dkmunzeemeetsdjurslandbirthdayparty34": 2027,
  "crazy8astpaulmunzeebirthdaycelebration": 2028,
  "dogdaysofsummer5": 2029,
  "einbonnerinbielefeld": 2030,
  "syntt8rieventti": 2031,
  "munzee8thbirthdaydebrecen": 2032,
  "marylandmunzeebirthdaycelebration": 2033,
  "happy8thbirthdayworkum": 2034,
  "cedarrapidsgoodmorning8thbirthdayparty": 2035,
  "4thannualcedarrapidsbirthdaybash": 2036,
  "lgasbacktothe80sbirthdayinshepparton": 2037,
  "mattsmunzeemeetupmwmb2019": 2038,
  "dkmunzeemeetsdjurslandbirthdayparty44": 2039,
  "allucaneatmunzeebday": 2040,
  "mattsmunzeemeetupdenmarkbirthday2019": 2041,
  "mattsmunzeemeetupcrazy8": 2042,
  "celebratemunzee8thbirthdayatthebash": 2043,
  "8udapestmunzeeszlinap": 2044,
  "crazy8beewallacrazy": 2045,
  "caverscottjoinsthemillionairesclub": 2046,
  "munzee8thbirthdayincalifornia": 2047,
  "lgaswestcoastflorida": 2048,
  "4thannualbirthdayluau": 2049,
  "txnationalsmoremunzeesday": 2050,
  "crazy8amplsmunzeebirthdaycelebration": 2051,
  "lgaskccelebration": 2052,
  "masmalltownsturbridge": 2053,
  "yorkshires8thbirthdayparty": 2054,
  "gdayyall": 2055,
  "celebrate8yearswithrebelgtpatsheetz": 2056,
  "totallyawesomemunzeebirthdayinkc": 2057,
  "stl2piratebash": 2058,
  "8vuotissynttrieventti": 2059,
  "sommereventimhainbymunzeeclanlm": 2060,
  "hellsinkigoesespoo": 2061,
  "ncmunzee8thbirthdaycelebration": 2062,
  "m8thpartillestadsparken": 2063,
  "wismalltownwestbend": 2064,
  "bowlrswifebirthdayandmeettheclanevent": 2065,
  "flsmalltowndadecity": 2066,
  "greermunzeehuntiii": 2067,
  "theperfectmunzeedaygreermunzeehuntiii": 2068,
  "vawoodboogersmalltownevent": 2069,
  "1ncmunzeefestival2019royalball": 2070,
  "2ncmunzeefestival2019": 2071,
  "3ncmunzeefestival2019crowningglory": 2072,
  "flbikinispeedobeachparty": 2073,
  "floridahappyhour": 2074,
  "munzeebashinthevillagesfl": 2075,
  "njsmalltownstanhope3": 2076,
  "treehouse": 2077,
  "treehouse1": 2077,
  "treehouse2": 2077,
  "treehouse3": 2077,
  "treehouse4": 2077,
  "treehouse5": 2077,
  "treehouse6": 2077,
  "treehouse7": 2077,
  "treehouse8": 2077,
  "treehouse9": 2077,
  "treehouse10": 2077,
  "stl1talklikeapirate": 2078,
  "autumnwave2": 2079,
  "stl3pirateslovetacos": 2080,
  "lasmalltownhoumabayoucountry": 2081,
  "byebyebash2019": 2082,
  "itsspookieroutwest": 2083,
  "bhamseptembermunzeelunch": 2084,
  "mhqbash2019registration": 2085,
  "mhqbash6eventzeefun": 2086,
  "mhqbash6andwallabash": 2087,
  "knightsgoblet2019": 2088,
  "thekingsfork": 2089,
  "mhqbash6fitness": 2090,
  "halloweenihobro2019": 2091,
  "romegamunzeemeetup": 2092,
  "texashalloween2019": 2093,
  "prattvillesspookygathering": 2094,
  "frightnightinkc": 2095,
  "hallobudapesthalloween": 2096,
  "aghoulishgoodtime": 2097,
  "bhamspookyscarylunch": 2098,
  "halloweenturku2019": 2099,
  "munzeedaystartupspartanburg": 2100,
  "chillinattheihop": 2101,
  "ahauntinginhampton": 2102,
  "desmoinesspooktacularhalloween": 2103,
  "amarylandmunzoweenspooktacular": 2104,
  "halloweenkaffinami": 2105,
  "saybooandmunzeeonberlin": 2106,
  "halloweenpartyworkum2019": 2107,
  "diadelosmunzees": 2108,
  "hotdiggitydog": 2109,
  "floridafrankenweenie": 2110,
  "halloweeninlithuania2019": 2111,
  "mcdougallghostsandgoblins": 2112,
  "zauberhaftetraubenlezeeevent1": 2113,
  "spooktaculartomkatzeeevent2": 2114,
  "vacationcondo": 2115,
  "vacationcondoroom": 2116,
  "witchplease": 2117,
  "tomcatcaterwaul": 2118,
  "ghoulsinorlando": 2119,
  "goblinsfordinnerinorlando": 2120,
  "allhallowsintherye": 2121,
  "battymexican": 2122,
  "octoberpumpkinfest": 2123,
  "awaterhalloweentownevent": 2124,
  "spookymawsonlakes2": 2125,
  "ymhhalloween2019": 2126,
  "pickyourpoisoninthealriverregion": 2127,
  "meetingnewscaryfriends": 2128,
  "zombiesarestilleatingmymunzees": 2129,
  "caterwaulinghallowzeen2": 2130,
  "possiblypoisonouspotions": 2131,
  "halloween2019praha": 2132,
  "newenglandmunzfestmeetgreet": 2133,
  "newenglandmunzfestsaturdayam": 2134,
  "newenglandmunzfestsaturdayafternoon": 2135,
  "newenglandmunzfestsaturdaypmthinkpink": 2136,
  "newenglandmunzfestsundayam": 2137,
  "gettinspookyinwatertown": 2138,
  "nchalloween": 2139,
  "theblackcatsbewitchment": 2140,
  "kysmalltowngeorgetownspooktacular": 2141,
  "palehalloween2019": 2142,
  "alabamariverregionpumpkinsplash": 2143,
  "bewitchedinthealabamarr": 2144,
  "ascarygoodtimeontheriver": 2145,
  "fallingforyouinkansascity": 2146,
  "puttlovescandy": 2147,
  "bhamgoblinsgyros": 2148,
  "autumnisfinallyheresomeoneisturning51": 2149,
  "meetengreetlelystad": 2150,
  "celebraterosieree": 2151,
  "blackfridayatkiwanisislandpark": 2152,
  "berlinerweihnachtsevent2019": 2153,
  "2starmotel": 2154,
  "2starmotelroom": 2155,
  "3starmotel": 2156,
  "3starmotelroom": 2157,
  "skyland": 2158,
  "skyland1": 2158,
  "skyland2": 2158,
  "skyland3": 2158,
  "skyland4": 2158,
  "skyland5": 2158,
  "skyland6": 2158,
  "skyland7": 2158,
  "skyland8": 2158,
  "skyland9": 2158,
  "skyland10": 2158,
  "magnet": 2159,
  "physicalmagnet": 2159,
  "virtualmagnet": 2160,
  "blastcapture": 2161,
  "blastcapturemini": 2162,
  "blastcapturemega": 2163,
  "destination": 2164,
  "securesocial": 2165,
  "virtualcolors": 2167,
  "upgrademyth": 2168,
  "evolutionreset": 2169,
  "zeds": 2170,
  "zodiac": 2171,
  "chinesezodiac": 2172,
  "physicaldeploybooster": 2174,
  "virtualdeploybooster": 2175,
  "physicalcapturebooster": 2176,
  "virtualcapturebooster": 2177
}