[
  {
    "name": "Virtual Emerald",
    "icon": "virtual_emerald",
    "id": 148
  },
  {
    "name": "Virtual Amethyst",
    "icon": "virtual_amethyst",
    "id": 290
  },
  {
    "name": "Flat Rob",
    "icon": "flatrob",
    "id": 353
  },
  {
    "name": "Virtual Trail",
    "icon": "virtual_trail",
    "id": 390
  },
  {
    "name": "Surprise",
    "icon": "surprise",
    "id": 400
  },
  {
    "name": "Virtual Resort",
    "icon": "virtual_resort",
    "id": 470
  },
  {
    "name": "Virtual Resort Room",
    "icon": "virtual_resort_room",
    "id": 471
  },
  {
    "name": "Event Trail",
    "icon": "eventtrail",
    "id": 600
  },
  {
    "name": "Carrot",
    "icon": "carrot",
    "id": 660
  },
  {
    "name": "Peas",
    "icon": "peas",
    "id": 661
  },
  {
    "name": "Carrot Seed",
    "icon": "carrotseed",
    "id": 664
  },
  {
    "name": "Peas Seed",
    "icon": "peasseed",
    "id": 665
  },
  {
    "name": "Carrot Plant",
    "icon": "carrotplant",
    "id": 668
  },
  {
    "name": "Peas Plant",
    "icon": "peasplant",
    "id": 669
  },
  {
    "name": "Virtual Sapphire",
    "icon": "virtual_sapphire",
    "id": 681
  },
  {
    "name": "TX Historical Location",
    "icon": "txhistoricallocation",
    "id": 682
  },
  {
    "name": "Championship Horse",
    "icon": "championshiphorse",
    "id": 702
  },
  {
    "name": "Eggs",
    "icon": "eggs",
    "id": 703
  },
  {
    "name": "Colt",
    "icon": "colt",
    "id": 704
  },
  {
    "name": "Chick",
    "icon": "chick",
    "id": 705
  },
  {
    "name": "Racehorse",
    "icon": "racehorse",
    "id": 706
  },
  {
    "name": "Chicken",
    "icon": "chicken",
    "id": 707
  },
  {
    "name": "Family",
    "icon": "family",
    "id": 735
  },
  {
    "name": "Field",
    "icon": "field",
    "id": 736
  },
  {
    "name": "Farmer",
    "icon": "farmer",
    "id": 737
  },
  {
    "name": "Farmer and Wife",
    "icon": "farmerandwife",
    "id": 738
  },
  {
    "name": "Potted Plant",
    "icon": "pottedplant",
    "id": 739
  },
  {
    "name": "Garden",
    "icon": "garden",
    "id": 740
  },
  {
    "name": "Submarine",
    "icon": "submarine",
    "id": 744
  },
  {
    "name": "Canoe",
    "icon": "canoe",
    "id": 745
  },
  {
    "name": "Motorboat",
    "icon": "motorboat",
    "id": 746
  },
  {
    "name": "POI Airport",
    "icon": "poiairport",
    "id": 782
  },
  {
    "name": "POI Sports",
    "icon": "poisports",
    "id": 783
  },
  {
    "name": "POI University",
    "icon": "poiuniversity",
    "id": 784
  },
  {
    "name": "POI Museum",
    "icon": "poimuseum",
    "id": 786
  },
  {
    "name": "POI Wildlife",
    "icon": "poiwildlife",
    "id": 787
  },
  {
    "name": "Muscle Car",
    "icon": "musclecar",
    "id": 807
  },
  {
    "name": "First Wheel",
    "icon": "firstwheel",
    "id": 808
  },
  {
    "name": "Penny-Farthing Bike",
    "icon": "penny-farthingbike",
    "id": 809
  },
  {
    "name": "Safari Bus",
    "icon": "safaribus",
    "id": 839
  },
  {
    "name": "Safari Truck",
    "icon": "safaritruck",
    "id": 840
  },
  {
    "name": "Safari Van",
    "icon": "safarivan",
    "id": 841
  },
  {
    "name": "Crossbow",
    "icon": "crossbow",
    "id": 998
  },
  {
    "name": "MHQ Flat Matt",
    "icon": "mhqflatmatt",
    "id": 1006
  },
  {
    "name": "MHQ Flat Rob",
    "icon": "mhqflatrob",
    "id": 1007
  },
  {
    "name": "Flat Matt",
    "icon": "flatmatt",
    "id": 1015
  },
  {
    "name": "Air Mystery",
    "icon": "airmystery",
    "id": 1086
  },
  {
    "name": "Feather",
    "icon": "feather",
    "id": 1087
  },
  {
    "name": "Golden Feather",
    "icon": "goldenfeather",
    "id": 1088
  },
  {
    "name": "Temporary Virtual",
    "icon": "temporaryvirtual",
    "id": 1245
  },
  {
    "name": "Catapult",
    "icon": "catapult",
    "id": 1248
  },
  {
    "name": "Flat Lou",
    "icon": "flatlou",
    "id": 1338
  },
  {
    "name": "POI Historical Place",
    "icon": "poihistoricalplace",
    "id": 1339
  },
  {
    "name": "POI Library",
    "icon": "poilibrary",
    "id": 1340
  },
  {
    "name": "POI First Responders",
    "icon": "poifirstresponders",
    "id": 1341
  },
  {
    "name": "POI Faith Place",
    "icon": "poifaithplace",
    "id": 1342
  },
  {
    "name": "Tower Bridge Flat Lou",
    "icon": "towerbridgeflatlou",
    "id": 1343
  },
  {
    "name": "Night Vision Goggles",
    "icon": "nightvisiongoggles",
    "id": 1359
  },
  {
    "name": "Virtual",
    "icon": "virtual",
    "id": 1409
  },
  {
    "name": "Virtual Rainbow",
    "icon": "virtual_rainbow",
    "id": 1410
  },
  {
    "name": "Virtual Timberwolf",
    "icon": "virtual_timberwolf",
    "id": 1411
  },
  {
    "name": "Virtual Silver",
    "icon": "virtual_silver",
    "id": 1412
  },
  {
    "name": "Virtual Gray",
    "icon": "virtual_gray",
    "id": 1413
  },
  {
    "name": "Virtual Black",
    "icon": "virtual_black",
    "id": 1414
  },
  {
    "name": "Virtual Orchid",
    "icon": "virtual_orchid",
    "id": 1415
  },
  {
    "name": "Virtual Wisteria",
    "icon": "virtual_wisteria",
    "id": 1416
  },
  {
    "name": "Virtual Purple Mountains Majesty",
    "icon": "virtual_purple_mountains_majesty",
    "id": 1417
  },
  {
    "name": "Virtual Violet",
    "icon": "virtual_violet",
    "id": 1418
  },
  {
    "name": "Virtual Plum",
    "icon": "virtual_plum",
    "id": 1419
  },
  {
    "name": "Virtual Blue Violet",
    "icon": "virtual_blue_violet",
    "id": 1420
  },
  {
    "name": "Virtual Blue",
    "icon": "virtual_blue",
    "id": 1421
  },
  {
    "name": "Virtual Cadet Blue",
    "icon": "virtual_cadet_blue",
    "id": 1423
  },
  {
    "name": "Virtual Periwinkle",
    "icon": "virtual_periwinkle",
    "id": 1424
  },
  {
    "name": "Virtual Cornflower",
    "icon": "virtual_cornflower",
    "id": 1425
  },
  {
    "name": "Virtual Blue Green",
    "icon": "virtual_blue_green",
    "id": 1426
  },
  {
    "name": "Virtual Pacific Blue",
    "icon": "virtual_pacific_blue",
    "id": 1427
  },
  {
    "name": "Virtual Cerulean",
    "icon": "virtual_cerulean",
    "id": 1428
  },
  {
    "name": "Virtual Robin Egg Blue",
    "icon": "virtual_robin_egg_blue",
    "id": 1429
  },
  {
    "name": "Virtual Indigo",
    "icon": "virtual_indigo",
    "id": 1430
  },
  {
    "name": "Virtual Turquoise Blue",
    "icon": "virtual_turquoise_blue",
    "id": 1431
  },
  {
    "name": "Virtual Sea Green",
    "icon": "virtual_sea_green",
    "id": 1432
  },
  {
    "name": "Virtual Granny Smith Apple",
    "icon": "virtual_granny_smith_apple",
    "id": 1433
  },
  {
    "name": "Virtual Green",
    "icon": "virtual_green",
    "id": 1434
  },
  {
    "name": "Virtual Forest Green",
    "icon": "virtual_forest_green",
    "id": 1435
  },
  {
    "name": "Virtual Asparagus",
    "icon": "virtual_asparagus",
    "id": 1436
  },
  {
    "name": "Virtual Olive Green",
    "icon": "virtual_olive_green",
    "id": 1437
  },
  {
    "name": "Virtual Yellow Green",
    "icon": "virtual_yellow_green",
    "id": 1438
  },
  {
    "name": "Virtual Green Yellow",
    "icon": "virtual_green_yellow",
    "id": 1439
  },
  {
    "name": "Virtual Spring Green",
    "icon": "virtual_spring_green",
    "id": 1440
  },
  {
    "name": "Virtual Gold",
    "icon": "virtual_gold",
    "id": 1441
  },
  {
    "name": "Virtual Yellow",
    "icon": "virtual_yellow",
    "id": 1442
  },
  {
    "name": "Virtual Goldenrod",
    "icon": "virtual_goldenrod",
    "id": 1443
  },
  {
    "name": "Virtual Dandelion",
    "icon": "virtual_dandelion",
    "id": 1444
  },
  {
    "name": "Virtual Orange",
    "icon": "virtual_orange",
    "id": 1445
  },
  {
    "name": "Virtual Burnt Orange",
    "icon": "virtual_burnt_orange",
    "id": 1446
  },
  {
    "name": "Virtual Melon",
    "icon": "virtual_melon",
    "id": 1448
  },
  {
    "name": "Virtual Pink",
    "icon": "virtual_pink",
    "id": 1449
  },
  {
    "name": "Virtual Carnation Pink",
    "icon": "virtual_carnation_pink",
    "id": 1450
  },
  {
    "name": "Virtual Mauvelous",
    "icon": "virtual_mauvelous",
    "id": 1451
  },
  {
    "name": "Virtual Salmon",
    "icon": "virtual_salmon",
    "id": 1452
  },
  {
    "name": "Virtual Tickle Me Pink",
    "icon": "virtual_tickle_me_pink",
    "id": 1453
  },
  {
    "name": "Virtual Magenta",
    "icon": "virtual_magenta",
    "id": 1454
  },
  {
    "name": "Virtual Wild Strawberry",
    "icon": "virtual_wild_strawberry",
    "id": 1455
  },
  {
    "name": "Virtual Violet Red",
    "icon": "virtual_violet_red",
    "id": 1456
  },
  {
    "name": "Virtual Red Violet",
    "icon": "virtual_red_violet",
    "id": 1457
  },
  {
    "name": "Virtual Apricot",
    "icon": "virtual_apricot",
    "id": 1458
  },
  {
    "name": "Virtual Peach",
    "icon": "virtual_peach",
    "id": 1459
  },
  {
    "name": "Virtual Macaroni and Cheese",
    "icon": "virtual_macaroni_and_cheese",
    "id": 1460
  },
  {
    "name": "Virtual Tan",
    "icon": "virtual_tan",
    "id": 1461
  },
  {
    "name": "Virtual Burnt Sienna",
    "icon": "virtual_burnt_sienna",
    "id": 1462
  },
  {
    "name": "Virtual Bittersweet",
    "icon": "virtual_bittersweet",
    "id": 1463
  },
  {
    "name": "Virtual Red Orange",
    "icon": "virtual_red_orange",
    "id": 1464
  },
  {
    "name": "Virtual Scarlet",
    "icon": "virtual_scarlet",
    "id": 1465
  },
  {
    "name": "Virtual Red",
    "icon": "virtual_red",
    "id": 1466
  },
  {
    "name": "Virtual Brick Red",
    "icon": "virtual_brick_red",
    "id": 1467
  },
  {
    "name": "Virtual Mahogany",
    "icon": "virtual_mahogany",
    "id": 1468
  },
  {
    "name": "Virtual Chestnut",
    "icon": "virtual_chestnut",
    "id": 1469
  },
  {
    "name": "Virtual Tumbleweed",
    "icon": "virtual_tumbleweed",
    "id": 1470
  },
  {
    "name": "Virtual Raw Sienna",
    "icon": "virtual_raw_sienna",
    "id": 1471
  },
  {
    "name": "Virtual Brown",
    "icon": "virtual_brown",
    "id": 1473
  },
  {
    "name": "FL Historical Location",
    "icon": "flhistoricallocation",
    "id": 1474
  },
  {
    "name": "CA Historical Location",
    "icon": "cahistoricallocation",
    "id": 1475
  },
  {
    "name": "POI Hospital",
    "icon": "poihospital",
    "id": 1486
  },
  {
    "name": "POI Post Office",
    "icon": "poipostoffice",
    "id": 1487
  },
  {
    "name": "POI Cemetery",
    "icon": "poicemetery",
    "id": 1488
  },
  {
    "name": "World Heritage Historical Location",
    "icon": "worldheritagehistoricallocation",
    "id": 1489
  },
  {
    "name": "POI Unique Attraction",
    "icon": "poiuniqueattraction",
    "id": 1551
  },
  {
    "name": "Great Britain Iconic Location",
    "icon": "greatbritainiconiclocation",
    "id": 1552
  },
  {
    "name": "Flat Hammock",
    "icon": "flathammock",
    "id": 1581
  },
  {
    "name": "Gettysburg Flat Hammock",
    "icon": "gettysburgflathammock",
    "id": 1582
  },
  {
    "name": "POI Virtual Garden",
    "icon": "poi_virtual_garden",
    "id": 1631
  },
  {
    "name": "Czech Republic Iconic Location",
    "icon": "czechrepubliciconiclocation",
    "id": 1767
  },
  {
    "name": "Slovakia Iconic Location",
    "icon": "slovakiaiconiclocation",
    "id": 1768
  },
  {
    "name": "POI Cinema",
    "icon": "poicinema",
    "id": 1770
  },
  {
    "name": "Carnation",
    "icon": "carnation",
    "id": 1797
  },
  {
    "name": "Carnation Seed",
    "icon": "carnationseed",
    "id": 1798
  },
  {
    "name": "Carnation Germination",
    "icon": "carnationgermination",
    "id": 1799
  },
  {
    "name": "Carnation Growth",
    "icon": "carnationgrowth",
    "id": 1800
  },
  {
    "name": "Carnation Bud",
    "icon": "carnationbud",
    "id": 1801
  },
  {
    "name": "Pink Carnation Blossom",
    "icon": "pinkcarnationblossom",
    "id": 1802
  },
  {
    "name": "Red Carnation Blossom",
    "icon": "redcarnationblossom",
    "id": 1803
  },
  {
    "name": "Violet Carnation Blossom",
    "icon": "violetcarnationblossom",
    "id": 1804
  },
  {
    "name": "White Carnation Blossom",
    "icon": "whitecarnationblossom",
    "id": 1805
  },
  {
    "name": "Yellow Carnation Blossom",
    "icon": "yellowcarnationblossom",
    "id": 1806
  },
  {
    "name": "Washington Iconic Location",
    "icon": "washingtoniconiclocation",
    "id": 1831
  },
  {
    "name": "POI Transportation",
    "icon": "poitransportation",
    "id": 1977
  },
  {
    "name": "POI Play Park",
    "icon": "poiplaypark",
    "id": 1978
  },
  {
    "name": "Joystick Virtual",
    "icon": "joystickvirtual",
    "id": 2002
  },
  {
    "name": "InternationElles Virtual",
    "icon": "internationellesvirtual",
    "id": 2047
  },
  {
    "name": "Vacation Condo",
    "icon": "vacationcondo",
    "id": 2183
  },
  {
    "name": "Vacation Condo Room",
    "icon": "vacationcondoroom",
    "id": 2184
  },
  {
    "name": "New Hampshire Iconic Location",
    "icon": "newhampshireiconiclocation",
    "id": 2196
  },
  {
    "name": "New Mexico Iconic Location",
    "icon": "newmexicoiconiclocation",
    "id": 2197
  },
  {
    "name": "Virtual Citrine",
    "icon": "virtual_citrine",
    "id": 2361
  },
  {
    "name": "Virtual Onyx",
    "icon": "virtual_onyx",
    "id": 2362
  },
  {
    "name": "Sir Prize Wheel",
    "icon": "sirprizewheel",
    "id": 2412
  }
]